[
  {
    "commonName": "River Birch",
    "scientificName": "Betula nigra",
    "genus": "Betula",
    "species": "nigra",
    "cultivar": "Dura Heat",
    "plantType": "tree",
    "category": "ornamental",
    "tags": ["heat-tolerant", "wet-soil-tolerant", "exfoliating-bark", "multi-stem"],
    "matureHeightMin": 30,
    "matureHeightMax": 40,
    "matureSpreadMin": 20,
    "matureSpreadMax": 30,
    "growthRate": "fast",
    "sunExposure": ["full-sun", "part-sun"],
    "waterNeeds": "moderate",
    "soilType": ["loam", "clay", "moist"],
    "evergreenOrDecid": "deciduous",
    "flowerColor": [],
    "foliageColor": ["green"],
    "fallColor": ["yellow"],
    "bloomSeason": [],
    "form": "upright, multi-stem",
    "pollinators": [],
    "wildlifeValue": [],
    "resistances": ["moderate-deer", "heat"],
    "commonSizes": [],
    "designUses": ["specimen", "shade", "accent"],
    "notes": "Tolerates wet soils; exfoliating bark; heat-tolerant selection. A heat-adapted river birch with beautiful peeling bark and strong resistance to leaf spot, ideal for tough Southern landscapes."
  },
  {
    "commonName": "European Hornbeam",
    "scientificName": "Carpinus betulus",
    "genus": "Carpinus",
    "species": "betulus",
    "cultivar": null,
    "plantType": "tree",
    "category": "ornamental",
    "tags": ["screening", "hedging", "formal", "dense-branching"],
    "matureHeightMin": 30,
    "matureHeightMax": 40,
    "matureSpreadMin": 20,
    "matureSpreadMax": 30,
    "growthRate": "moderate",
    "sunExposure": ["full-sun", "part-shade"],
    "waterNeeds": "moderate",
    "soilType": ["loam", "clay", "well-drained"],
    "evergreenOrDecid": "deciduous",
    "flowerColor": [],
    "foliageColor": ["green"],
    "fallColor": ["yellow"],
    "bloomSeason": [],
    "form": "dense, oval to rounded",
    "pollinators": [],
    "wildlifeValue": [],
    "resistances": ["deer", "drought-moderate"],
    "commonSizes": [],
    "designUses": ["screen", "hedge", "specimen", "foundation"],
    "notes": "Excellent for screening, hedging, and formal landscapes. A refined, durable tree with dense branching and smooth gray bark, perfect for structured or architectural plantings."
  },
  {
    "commonName": "Fastigiata Hornbeam",
    "scientificName": "Carpinus betulus",
    "genus": "Carpinus",
    "species": "betulus",
    "cultivar": "Fastigiata",
    "plantType": "tree",
    "category": "ornamental",
    "tags": ["columnar", "narrow", "formal", "architectural"],
    "matureHeightMin": 30,
    "matureHeightMax": 40,
    "matureSpreadMin": 15,
    "matureSpreadMax": 20,
    "growthRate": "moderate",
    "sunExposure": ["full-sun", "part-shade"],
    "waterNeeds": "moderate",
    "soilType": ["loam", "clay", "well-drained"],
    "evergreenOrDecid": "deciduous",
    "flowerColor": [],
    "foliageColor": ["green"],
    "fallColor": ["yellow"],
    "bloomSeason": [],
    "form": "columnar",
    "pollinators": [],
    "wildlifeValue": [],
    "resistances": ["deer"],
    "commonSizes": [],
    "designUses": ["screen", "hedge", "accent", "border"],
    "notes": "Ideal for tight spaces, allees, and formal screens. A stately, columnar hornbeam with dense foliage and a clean architectural form that holds its shape beautifully."
  },
  {
    "commonName": "Tuscarora Crape Myrtle",
    "scientificName": "Lagerstroemia indica",
    "genus": "Lagerstroemia",
    "species": "indica",
    "cultivar": "Tuscarora",
    "plantType": "tree",
    "category": "ornamental",
    "tags": ["summer-blooming", "mildew-resistant", "low-maintenance"],
    "matureHeightMin": 15,
    "matureHeightMax": 20,
    "matureSpreadMin": 10,
    "matureSpreadMax": 15,
    "growthRate": "fast",
    "sunExposure": ["full-sun"],
    "waterNeeds": "low",
    "soilType": ["loam", "clay", "well-drained"],
    "evergreenOrDecid": "deciduous",
    "flowerColor": ["coral-pink"],
    "foliageColor": ["green"],
    "fallColor": ["orange", "red"],
    "bloomSeason": ["summer", "late-summer"],
    "form": "upright, vase-shaped",
    "pollinators": ["bees", "butterflies"],
    "wildlifeValue": [],
    "resistances": ["deer", "drought", "mildew"],
    "commonSizes": [],
    "designUses": ["specimen", "accent", "border"],
    "notes": "Mildew-resistant; excellent summer color. A vibrant coral-pink crape myrtle with strong disease resistance and a graceful vase shape."
  },
  {
    "commonName": "Twilight Crape Myrtle",
    "scientificName": "Lagerstroemia indica",
    "genus": "Lagerstroemia",
    "species": "indica",
    "cultivar": "Twilight",
    "plantType": "tree",
    "category": "ornamental",
    "tags": ["summer-blooming", "purple-flower", "statement-plant"],
    "matureHeightMin": 20,
    "matureHeightMax": 25,
    "matureSpreadMin": 15,
    "matureSpreadMax": 20,
    "growthRate": "fast",
    "sunExposure": ["full-sun"],
    "waterNeeds": "low",
    "soilType": ["loam", "clay", "well-drained"],
    "evergreenOrDecid": "deciduous",
    "flowerColor": ["deep-purple"],
    "foliageColor": ["green"],
    "fallColor": ["orange", "red"],
    "bloomSeason": ["summer"],
    "form": "upright, rounded",
    "pollinators": ["bees", "butterflies"],
    "wildlifeValue": [],
    "resistances": ["deer", "drought"],
    "commonSizes": [],
    "designUses": ["specimen", "accent"],
    "notes": "One of the truest purple-flowering crape myrtles. A standout purple-blooming crape myrtle with rich color and a strong, rounded canopy."
  },
  {
    "commonName": "Muskogee Crape Myrtle",
    "scientificName": "Lagerstroemia hybrid",
    "genus": "Lagerstroemia",
    "species": "hybrid",
    "cultivar": "Muskogee",
    "plantType": "tree",
    "category": "ornamental",
    "tags": ["summer-blooming", "long-blooming", "mildew-resistant"],
    "matureHeightMin": 20,
    "matureHeightMax": 25,
    "matureSpreadMin": 15,
    "matureSpreadMax": 20,
    "growthRate": "fast",
    "sunExposure": ["full-sun"],
    "waterNeeds": "low",
    "soilType": ["loam", "clay", "well-drained"],
    "evergreenOrDecid": "deciduous",
    "flowerColor": ["lavender"],
    "foliageColor": ["green"],
    "fallColor": ["orange", "red"],
    "bloomSeason": ["summer", "late-summer"],
    "form": "upright, spreading",
    "pollinators": ["bees", "butterflies"],
    "wildlifeValue": [],
    "resistances": ["deer", "drought", "mildew"],
    "commonSizes": [],
    "designUses": ["specimen", "accent", "shade"],
    "notes": "One of the longest-blooming crape myrtles. A vigorous, mildew-resistant crape myrtle with soft lavender blooms that persist for months."
  },
  {
    "commonName": "Natchez Crape Myrtle",
    "scientificName": "Lagerstroemia hybrid",
    "genus": "Lagerstroemia",
    "species": "hybrid",
    "cultivar": "Natchez",
    "plantType": "tree",
    "category": "ornamental",
    "tags": ["summer-blooming", "exfoliating-bark", "year-round-interest"],
    "matureHeightMin": 25,
    "matureHeightMax": 30,
    "matureSpreadMin": 20,
    "matureSpreadMax": 25,
    "growthRate": "fast",
    "sunExposure": ["full-sun"],
    "waterNeeds": "low",
    "soilType": ["loam", "clay", "well-drained"],
    "evergreenOrDecid": "deciduous",
    "flowerColor": ["white"],
    "foliageColor": ["green"],
    "fallColor": ["orange", "red"],
    "bloomSeason": ["summer", "late-summer"],
    "form": "broad, arching",
    "pollinators": ["bees", "butterflies"],
    "wildlifeValue": [],
    "resistances": ["deer", "drought"],
    "commonSizes": [],
    "designUses": ["specimen", "accent", "shade"],
    "notes": "Famous cinnamon-colored exfoliating bark. A large, elegant crape myrtle with bright white blooms and striking cinnamon bark that provides year-round interest."
  },
  {
    "commonName": "Tonto Crape Myrtle",
    "scientificName": "Lagerstroemia indica",
    "genus": "Lagerstroemia",
    "species": "indica",
    "cultivar": "Tonto",
    "plantType": "tree",
    "category": "ornamental",
    "tags": ["compact", "mildew-resistant", "summer-blooming"],
    "matureHeightMin": 8,
    "matureHeightMax": 12,
    "matureSpreadMin": 6,
    "matureSpreadMax": 10,
    "growthRate": "moderate",
    "sunExposure": ["full-sun"],
    "waterNeeds": "low",
    "soilType": ["loam", "clay", "well-drained"],
    "evergreenOrDecid": "deciduous",
    "flowerColor": ["fuchsia-red"],
    "foliageColor": ["green"],
    "fallColor": ["orange", "red"],
    "bloomSeason": ["summer"],
    "form": "rounded",
    "pollinators": ["bees", "butterflies"],
    "wildlifeValue": [],
    "resistances": ["deer", "drought", "mildew"],
    "commonSizes": [],
    "designUses": ["accent", "border", "foundation", "mass-planting"],
    "notes": "Compact and mildew-resistant. A compact crape myrtle with vivid red blooms and excellent disease resistance, ideal for smaller landscapes."
  },
  {
    "commonName": "Coral Magic Crape Myrtle",
    "scientificName": "Lagerstroemia hybrid",
    "genus": "Lagerstroemia",
    "species": "hybrid",
    "cultivar": "Coral Magic",
    "plantType": "tree",
    "category": "ornamental",
    "tags": ["compact", "early-blooming", "dense-foliage"],
    "matureHeightMin": 6,
    "matureHeightMax": 10,
    "matureSpreadMin": 6,
    "matureSpreadMax": 8,
    "growthRate": "moderate",
    "sunExposure": ["full-sun"],
    "waterNeeds": "low",
    "soilType": ["loam", "clay", "well-drained"],
    "evergreenOrDecid": "deciduous",
    "flowerColor": ["coral-pink"],
    "foliageColor": ["green"],
    "fallColor": ["orange"],
    "bloomSeason": ["late-spring", "summer"],
    "form": "rounded, compact",
    "pollinators": ["bees", "butterflies"],
    "wildlifeValue": [],
    "resistances": ["deer", "drought"],
    "commonSizes": [],
    "designUses": ["accent", "foundation", "border", "container"],
    "notes": "Early blooming; dense foliage. A compact, early-blooming crape myrtle with bright coral flowers and a tidy, rounded habit."
  },
  {
    "commonName": "Autaugaville Purple Crape Myrtle",
    "scientificName": "Lagerstroemia indica",
    "genus": "Lagerstroemia",
    "species": "indica",
    "cultivar": "Autaugaville",
    "plantType": "tree",
    "category": "ornamental",
    "tags": ["summer-blooming", "purple-flower", "strong-color"],
    "matureHeightMin": 12,
    "matureHeightMax": 15,
    "matureSpreadMin": 8,
    "matureSpreadMax": 12,
    "growthRate": "moderate",
    "sunExposure": ["full-sun"],
    "waterNeeds": "low",
    "soilType": ["loam", "clay", "well-drained"],
    "evergreenOrDecid": "deciduous",
    "flowerColor": ["deep-purple"],
    "foliageColor": ["green"],
    "fallColor": ["orange", "red"],
    "bloomSeason": ["summer"],
    "form": "upright, rounded",
    "pollinators": ["bees", "butterflies"],
    "wildlifeValue": [],
    "resistances": ["deer", "drought"],
    "commonSizes": [],
    "designUses": ["specimen", "accent"],
    "notes": "Strong purple coloration. A richly colored purple crape myrtle with a balanced, upright form and excellent summer performance."
  },
  {
    "commonName": "Sioux Pink Crape Myrtle",
    "scientificName": "Lagerstroemia indica",
    "genus": "Lagerstroemia",
    "species": "indica",
    "cultivar": "Sioux",
    "plantType": "tree",
    "category": "ornamental",
    "tags": ["summer-blooming", "mildew-resistant", "refined"],
    "matureHeightMin": 12,
    "matureHeightMax": 15,
    "matureSpreadMin": 8,
    "matureSpreadMax": 10,
    "growthRate": "moderate",
    "sunExposure": ["full-sun"],
    "waterNeeds": "low",
    "soilType": ["loam", "clay", "well-drained"],
    "evergreenOrDecid": "deciduous",
    "flowerColor": ["bright-pink"],
    "foliageColor": ["green"],
    "fallColor": ["orange", "red"],
    "bloomSeason": ["summer"],
    "form": "upright, oval",
    "pollinators": ["bees", "butterflies"],
    "wildlifeValue": [],
    "resistances": ["deer", "drought", "mildew"],
    "commonSizes": [],
    "designUses": ["specimen", "accent", "border"],
    "notes": "Excellent mildew resistance. A bright pink crape myrtle with strong disease resistance and a refined, upright habit."
  },
  {
    "commonName": "Sun Valley Red Maple",
    "scientificName": "Acer rubrum",
    "genus": "Acer",
    "species": "rubrum",
    "cultivar": "Sun Valley",
    "plantType": "tree",
    "category": "ornamental",
    "tags": ["seedless", "fall-color", "symmetrical"],
    "matureHeightMin": 40,
    "matureHeightMax": 50,
    "matureSpreadMin": 30,
    "matureSpreadMax": 40,
    "growthRate": "moderate",
    "sunExposure": ["full-sun"],
    "waterNeeds": "moderate",
    "soilType": ["loam", "clay", "moist", "well-drained"],
    "evergreenOrDecid": "deciduous",
    "flowerColor": ["red"],
    "foliageColor": ["green"],
    "fallColor": ["red"],
    "bloomSeason": ["early-spring"],
    "form": "oval",
    "pollinators": [],
    "wildlifeValue": [],
    "resistances": ["moderate-deer"],
    "commonSizes": [],
    "designUses": ["shade", "specimen", "accent"],
    "notes": "Seedless; brilliant red fall color. A seedless red maple known for its uniform shape and intense red fall foliage."
  },
  {
    "commonName": "Legacy Sugar Maple",
    "scientificName": "Acer saccharum",
    "genus": "Acer",
    "species": "saccharum",
    "cultivar": "Legacy",
    "plantType": "tree",
    "category": "ornamental",
    "tags": ["heat-tolerant", "fall-color", "glossy-foliage"],
    "matureHeightMin": 50,
    "matureHeightMax": 60,
    "matureSpreadMin": 35,
    "matureSpreadMax": 40,
    "growthRate": "moderate",
    "sunExposure": ["full-sun"],
    "waterNeeds": "moderate",
    "soilType": ["loam", "well-drained"],
    "evergreenOrDecid": "deciduous",
    "flowerColor": ["yellow-green"],
    "foliageColor": ["green"],
    "fallColor": ["golden", "orange"],
    "bloomSeason": ["spring"],
    "form": "broadly oval",
    "pollinators": [],
    "wildlifeValue": [],
    "resistances": ["moderate-deer", "heat"],
    "commonSizes": [],
    "designUses": ["shade", "specimen"],
    "notes": "Heat-tolerant sugar maple selection. A tough, heat-tolerant sugar maple with glossy foliage and outstanding golden-orange fall color."
  },
  {
    "commonName": "Autumn Brilliance Serviceberry",
    "scientificName": "Amelanchier grandiflora",
    "genus": "Amelanchier",
    "species": "grandiflora",
    "cultivar": "Autumn Brilliance",
    "plantType": "tree",
    "category": "native",
    "tags": ["four-season", "edible-berries", "fall-color", "multi-stem"],
    "matureHeightMin": 15,
    "matureHeightMax": 25,
    "matureSpreadMin": 10,
    "matureSpreadMax": 15,
    "growthRate": "moderate",
    "sunExposure": ["full-sun", "part-shade"],
    "waterNeeds": "moderate",
    "soilType": ["loam", "well-drained"],
    "evergreenOrDecid": "deciduous",
    "flowerColor": ["white"],
    "foliageColor": ["green"],
    "fallColor": ["red", "orange"],
    "bloomSeason": ["early-spring"],
    "form": "upright, multi-stem",
    "pollinators": ["bees", "butterflies"],
    "wildlifeValue": ["birds"],
    "resistances": ["moderate-deer"],
    "commonSizes": [],
    "designUses": ["specimen", "accent", "border"],
    "notes": "Edible berries; exceptional red-orange fall color. A four-season native tree with early white blooms, edible berries, and brilliant fall color."
  },
  {
    "commonName": "Venus Dogwood",
    "scientificName": "Cornus kousa x nuttallii",
    "genus": "Cornus",
    "species": "kousa x nuttallii",
    "cultivar": "Venus",
    "plantType": "tree",
    "category": "ornamental",
    "tags": ["disease-resistant", "large-blooms", "show-stopping"],
    "matureHeightMin": 15,
    "matureHeightMax": 20,
    "matureSpreadMin": 15,
    "matureSpreadMax": 20,
    "growthRate": "moderate",
    "sunExposure": ["full-sun", "part-shade"],
    "waterNeeds": "moderate",
    "soilType": ["loam", "well-drained", "acidic"],
    "evergreenOrDecid": "deciduous",
    "flowerColor": ["white"],
    "foliageColor": ["green"],
    "fallColor": ["red", "purple"],
    "bloomSeason": ["late-spring"],
    "form": "rounded",
    "pollinators": ["bees"],
    "wildlifeValue": ["birds"],
    "resistances": ["moderate-deer", "disease"],
    "commonSizes": [],
    "designUses": ["specimen", "accent"],
    "notes": "Massive blooms; highly disease resistant. A show-stopping dogwood with enormous white blooms and excellent disease resistance."
  },
  {
    "commonName": "Green Sleeves Dogwood",
    "scientificName": "Cornus florida",
    "genus": "Cornus",
    "species": "florida",
    "cultivar": "Green Sleeves",
    "plantType": "tree",
    "category": "native",
    "tags": ["unique-bloom", "understory"],
    "matureHeightMin": 15,
    "matureHeightMax": 20,
    "matureSpreadMin": 15,
    "matureSpreadMax": 20,
    "growthRate": "slow",
    "sunExposure": ["part-shade", "full-sun"],
    "waterNeeds": "moderate",
    "soilType": ["loam", "well-drained", "acidic", "moist"],
    "evergreenOrDecid": "deciduous",
    "flowerColor": ["greenish-white"],
    "foliageColor": ["green"],
    "fallColor": ["red"],
    "bloomSeason": ["spring"],
    "form": "rounded",
    "pollinators": ["bees"],
    "wildlifeValue": ["birds"],
    "resistances": ["moderate-deer"],
    "commonSizes": [],
    "designUses": ["specimen", "accent", "foundation"],
    "notes": "Unique green-tinted blooms. A distinctive flowering dogwood with soft green-tinted bracts that mature to creamy white."
  },
  {
    "commonName": "Weeping Willow",
    "scientificName": "Salix babylonica",
    "genus": "Salix",
    "species": "babylonica",
    "cultivar": null,
    "plantType": "tree",
    "category": "ornamental",
    "tags": ["fast-growing", "wet-soil-tolerant", "graceful"],
    "matureHeightMin": 30,
    "matureHeightMax": 40,
    "matureSpreadMin": 30,
    "matureSpreadMax": 40,
    "growthRate": "fast",
    "sunExposure": ["full-sun"],
    "waterNeeds": "high",
    "soilType": ["loam", "clay", "moist"],
    "evergreenOrDecid": "deciduous",
    "flowerColor": [],
    "foliageColor": ["green"],
    "fallColor": ["yellow"],
    "bloomSeason": [],
    "form": "weeping",
    "pollinators": [],
    "wildlifeValue": [],
    "resistances": [],
    "commonSizes": [],
    "designUses": ["specimen", "shade"],
    "notes": "Thrives in wet soils; fast-growing. A graceful, fast-growing tree with long, pendulous branches that thrive in moist areas."
  },
  {
    "commonName": "Nuttall Oak",
    "scientificName": "Quercus texana",
    "genus": "Quercus",
    "species": "texana",
    "cultivar": null,
    "plantType": "tree",
    "category": "native",
    "tags": ["fast-growing", "fall-color", "adaptable"],
    "matureHeightMin": 40,
    "matureHeightMax": 60,
    "matureSpreadMin": 25,
    "matureSpreadMax": 35,
    "growthRate": "fast",
    "sunExposure": ["full-sun"],
    "waterNeeds": "moderate",
    "soilType": ["loam", "clay", "moist", "well-drained"],
    "evergreenOrDecid": "deciduous",
    "flowerColor": [],
    "foliageColor": ["green"],
    "fallColor": ["red"],
    "bloomSeason": [],
    "form": "upright, oval",
    "pollinators": [],
    "wildlifeValue": ["birds"],
    "resistances": ["deer", "drought"],
    "commonSizes": [],
    "designUses": ["shade", "specimen"],
    "notes": "Fast-growing; excellent red fall color. A strong, adaptable oak with fast growth and vibrant red fall foliage."
  },
  {
    "commonName": "Everclear Elm",
    "scientificName": "Ulmus parvifolia",
    "genus": "Ulmus",
    "species": "parvifolia",
    "cultivar": "Emer II",
    "trademark": "Everclear速",
    "plantType": "tree",
    "category": "ornamental",
    "tags": ["columnar", "disease-resistant", "street-tree", "mottled-bark"],
    "matureHeightMin": 35,
    "matureHeightMax": 45,
    "matureSpreadMin": 15,
    "matureSpreadMax": 20,
    "growthRate": "moderate",
    "sunExposure": ["full-sun"],
    "waterNeeds": "low",
    "soilType": ["loam", "clay", "well-drained"],
    "evergreenOrDecid": "deciduous",
    "flowerColor": [],
    "foliageColor": ["green"],
    "fallColor": ["yellow"],
    "bloomSeason": [],
    "form": "columnar",
    "pollinators": [],
    "wildlifeValue": [],
    "resistances": ["deer", "drought", "disease"],
    "commonSizes": [],
    "designUses": ["screen", "specimen", "accent"],
    "notes": "Highly disease resistant; excellent street tree. A narrow, upright Chinese elm with exceptional disease resistance and attractive mottled bark."
  },
  {
    "commonName": "Yoshino Cherry",
    "scientificName": "Prunus yedoensis",
    "genus": "Prunus",
    "species": "yedoensis",
    "cultivar": null,
    "plantType": "tree",
    "category": "ornamental",
    "tags": ["spring-blooming", "mass-bloom", "iconic"],
    "matureHeightMin": 25,
    "matureHeightMax": 35,
    "matureSpreadMin": 20,
    "matureSpreadMax": 30,
    "growthRate": "moderate",
    "sunExposure": ["full-sun"],
    "waterNeeds": "moderate",
    "soilType": ["loam", "well-drained"],
    "evergreenOrDecid": "deciduous",
    "flowerColor": ["pale-pink", "white"],
    "foliageColor": ["green"],
    "fallColor": ["yellow"],
    "bloomSeason": ["early-spring"],
    "form": "rounded, spreading",
    "pollinators": ["bees"],
    "wildlifeValue": [],
    "resistances": [],
    "commonSizes": [],
    "designUses": ["specimen", "accent"],
    "notes": "Famous for mass spring bloom. A beloved flowering cherry known for its clouds of pale pink blooms in early spring."
  },
  {
    "commonName": "Kwanzan Cherry",
    "scientificName": "Prunus serrulata",
    "genus": "Prunus",
    "species": "serrulata",
    "cultivar": "Kwanzan",
    "plantType": "tree",
    "category": "ornamental",
    "tags": ["double-bloom", "spring-blooming", "showy"],
    "matureHeightMin": 20,
    "matureHeightMax": 30,
    "matureSpreadMin": 15,
    "matureSpreadMax": 25,
    "growthRate": "moderate",
    "sunExposure": ["full-sun"],
    "waterNeeds": "moderate",
    "soilType": ["loam", "well-drained"],
    "evergreenOrDecid": "deciduous",
    "flowerColor": ["pink"],
    "foliageColor": ["green"],
    "fallColor": ["orange", "yellow"],
    "bloomSeason": ["spring"],
    "form": "upright, vase-shaped",
    "pollinators": ["bees"],
    "wildlifeValue": [],
    "resistances": [],
    "commonSizes": [],
    "designUses": ["specimen", "accent"],
    "notes": "Double blooms resemble pom-poms. A showy cherry tree with large, double pink blossoms that create a dramatic spring display."
  },
  {
    "commonName": "Autumnalis Cherry",
    "scientificName": "Prunus subhirtella",
    "genus": "Prunus",
    "species": "subhirtella",
    "cultivar": "Autumnalis",
    "plantType": "tree",
    "category": "ornamental",
    "tags": ["twice-blooming", "fall-blooming", "spring-blooming"],
    "matureHeightMin": 20,
    "matureHeightMax": 30,
    "matureSpreadMin": 15,
    "matureSpreadMax": 25,
    "growthRate": "moderate",
    "sunExposure": ["full-sun"],
    "waterNeeds": "moderate",
    "soilType": ["loam", "well-drained"],
    "evergreenOrDecid": "deciduous",
    "flowerColor": ["pink"],
    "foliageColor": ["green"],
    "fallColor": ["yellow"],
    "bloomSeason": ["fall", "spring"],
    "form": "rounded",
    "pollinators": ["bees"],
    "wildlifeValue": [],
    "resistances": [],
    "commonSizes": [],
    "designUses": ["specimen", "accent"],
    "notes": "Blooms twice a year. A unique cherry that flowers lightly in fall and again in spring, extending the bloom season."
  },
  {
    "commonName": "Peggy Clarke Apricot",
    "scientificName": "Prunus mume",
    "genus": "Prunus",
    "species": "mume",
    "cultivar": "Peggy Clarke",
    "plantType": "tree",
    "category": "ornamental",
    "tags": ["winter-blooming", "fragrant", "early-interest"],
    "matureHeightMin": 15,
    "matureHeightMax": 20,
    "matureSpreadMin": 10,
    "matureSpreadMax": 15,
    "growthRate": "moderate",
    "sunExposure": ["full-sun"],
    "waterNeeds": "moderate",
    "soilType": ["loam", "well-drained"],
    "evergreenOrDecid": "deciduous",
    "flowerColor": ["rose-pink"],
    "foliageColor": ["green"],
    "fallColor": ["yellow"],
    "bloomSeason": ["winter"],
    "form": "upright, rounded",
    "pollinators": ["bees"],
    "wildlifeValue": [],
    "resistances": [],
    "commonSizes": [],
    "designUses": ["specimen", "accent"],
    "notes": "Highly fragrant winter blooms. A winter-blooming apricot with intensely fragrant rose-pink flowers that appear before the leaves."
  },
  {
    "commonName": "Pink Cascade Weeping Cherry",
    "scientificName": "Prunus hybrid",
    "genus": "Prunus",
    "species": "hybrid",
    "cultivar": "Pink Cascade",
    "plantType": "tree",
    "category": "ornamental",
    "tags": ["weeping", "spring-blooming", "compact", "graceful"],
    "matureHeightMin": 12,
    "matureHeightMax": 15,
    "matureSpreadMin": 12,
    "matureSpreadMax": 15,
    "growthRate": "moderate",
    "sunExposure": ["full-sun"],
    "waterNeeds": "moderate",
    "soilType": ["loam", "well-drained"],
    "evergreenOrDecid": "deciduous",
    "flowerColor": ["soft-pink"],
    "foliageColor": ["green"],
    "fallColor": ["yellow"],
    "bloomSeason": ["early-spring"],
    "form": "weeping",
    "pollinators": ["bees"],
    "wildlifeValue": [],
    "resistances": [],
    "commonSizes": [],
    "designUses": ["specimen", "accent"],
    "notes": "Graceful cascading branches. A compact weeping cherry with soft pink spring blooms and elegant, fountain-like branching."
  },
  {
    "commonName": "Snow Fountain Weeping Cherry",
    "scientificName": "Prunus hybrid",
    "genus": "Prunus",
    "species": "hybrid",
    "cultivar": "Snofozam",
    "trademark": "Snow Fountains速",
    "plantType": "tree",
    "category": "ornamental",
    "tags": ["weeping", "spring-blooming", "compact", "heavy-bloom"],
    "matureHeightMin": 8,
    "matureHeightMax": 15,
    "matureSpreadMin": 6,
    "matureSpreadMax": 12,
    "growthRate": "moderate",
    "sunExposure": ["full-sun"],
    "waterNeeds": "moderate",
    "soilType": ["loam", "well-drained"],
    "evergreenOrDecid": "deciduous",
    "flowerColor": ["white"],
    "foliageColor": ["green"],
    "fallColor": ["yellow", "orange"],
    "bloomSeason": ["early-spring"],
    "form": "weeping",
    "pollinators": ["bees"],
    "wildlifeValue": [],
    "resistances": [],
    "commonSizes": [],
    "designUses": ["specimen", "accent", "container"],
    "notes": "Heavy spring bloom; compact form. A popular weeping cherry with cascading branches covered in pure white spring flowers."
  },
  {
    "commonName": "Hearts of Gold Redbud",
    "scientificName": "Cercis canadensis",
    "genus": "Cercis",
    "species": "canadensis",
    "cultivar": "Hearts of Gold",
    "plantType": "tree",
    "category": "native",
    "tags": ["golden-foliage", "spring-blooming", "colorful-foliage"],
    "matureHeightMin": 15,
    "matureHeightMax": 20,
    "matureSpreadMin": 15,
    "matureSpreadMax": 20,
    "growthRate": "moderate",
    "sunExposure": ["full-sun", "part-shade"],
    "waterNeeds": "moderate",
    "soilType": ["loam", "well-drained"],
    "evergreenOrDecid": "deciduous",
    "flowerColor": ["lavender-pink"],
    "foliageColor": ["golden"],
    "fallColor": ["yellow"],
    "bloomSeason": ["early-spring"],
    "form": "rounded",
    "pollinators": ["bees", "butterflies"],
    "wildlifeValue": [],
    "resistances": ["moderate-deer"],
    "commonSizes": [],
    "designUses": ["specimen", "accent"],
    "notes": "Bright golden new foliage. A colorful redbud with lavender spring blooms and brilliant golden foliage that holds color well."
  },
  {
    "commonName": "Zig Zag Redbud",
    "scientificName": "Cercis canadensis",
    "genus": "Cercis",
    "species": "canadensis",
    "cultivar": "Zig Zag",
    "plantType": "tree",
    "category": "native",
    "tags": ["architectural", "unique-branching", "spring-blooming"],
    "matureHeightMin": 12,
    "matureHeightMax": 15,
    "matureSpreadMin": 10,
    "matureSpreadMax": 12,
    "growthRate": "slow",
    "sunExposure": ["full-sun", "part-shade"],
    "waterNeeds": "moderate",
    "soilType": ["loam", "well-drained"],
    "evergreenOrDecid": "deciduous",
    "flowerColor": ["pink"],
    "foliageColor": ["green"],
    "fallColor": ["yellow"],
    "bloomSeason": ["early-spring"],
    "form": "irregular",
    "pollinators": ["bees", "butterflies"],
    "wildlifeValue": [],
    "resistances": ["moderate-deer"],
    "commonSizes": [],
    "designUses": ["specimen", "accent"],
    "notes": "Unique architectural branching. A distinctive redbud with quirky, angular branching and classic pink spring blooms."
  },
  {
    "commonName": "Appalachian Red Redbud",
    "scientificName": "Cercis canadensis",
    "genus": "Cercis",
    "species": "canadensis",
    "cultivar": "Appalachian Red",
    "plantType": "tree",
    "category": "native",
    "tags": ["vivid-bloom", "spring-blooming", "showy"],
    "matureHeightMin": 15,
    "matureHeightMax": 20,
    "matureSpreadMin": 15,
    "matureSpreadMax": 20,
    "growthRate": "moderate",
    "sunExposure": ["full-sun", "part-shade"],
    "waterNeeds": "moderate",
    "soilType": ["loam", "well-drained"],
    "evergreenOrDecid": "deciduous",
    "flowerColor": ["magenta-red"],
    "foliageColor": ["green"],
    "fallColor": ["yellow"],
    "bloomSeason": ["early-spring"],
    "form": "rounded",
    "pollinators": ["bees", "butterflies"],
    "wildlifeValue": [],
    "resistances": ["moderate-deer"],
    "commonSizes": [],
    "designUses": ["specimen", "accent"],
    "notes": "One of the brightest redbud bloom colors. A striking redbud known for its intensely vivid magenta-red spring flowers."
  },
  {
    "commonName": "Merlot Redbud",
    "scientificName": "Cercis canadensis",
    "genus": "Cercis",
    "species": "canadensis",
    "cultivar": "Merlot",
    "plantType": "tree",
    "category": "native",
    "tags": ["burgundy-foliage", "drought-tolerant", "compact"],
    "matureHeightMin": 12,
    "matureHeightMax": 15,
    "matureSpreadMin": 12,
    "matureSpreadMax": 15,
    "growthRate": "moderate",
    "sunExposure": ["full-sun", "part-shade"],
    "waterNeeds": "low",
    "soilType": ["loam", "well-drained"],
    "evergreenOrDecid": "deciduous",
    "flowerColor": ["rosy-pink"],
    "foliageColor": ["burgundy"],
    "fallColor": ["yellow"],
    "bloomSeason": ["early-spring"],
    "form": "rounded",
    "pollinators": ["bees", "butterflies"],
    "wildlifeValue": [],
    "resistances": ["moderate-deer", "drought"],
    "commonSizes": [],
    "designUses": ["specimen", "accent"],
    "notes": "Glossy burgundy foliage; drought tolerant. A compact redbud with glossy, wine-colored foliage and rosy-pink blooms."
  },
  {
    "commonName": "Eastern Redbud",
    "scientificName": "Cercis canadensis",
    "genus": "Cercis",
    "species": "canadensis",
    "cultivar": null,
    "plantType": "tree",
    "category": "native",
    "tags": ["native", "pollinator", "spring-blooming", "early-bloom"],
    "matureHeightMin": 20,
    "matureHeightMax": 30,
    "matureSpreadMin": 20,
    "matureSpreadMax": 30,
    "growthRate": "moderate",
    "sunExposure": ["full-sun", "part-shade"],
    "waterNeeds": "moderate",
    "soilType": ["loam", "clay", "well-drained"],
    "evergreenOrDecid": "deciduous",
    "flowerColor": ["pink"],
    "foliageColor": ["green"],
    "fallColor": ["yellow"],
    "bloomSeason": ["early-spring"],
    "form": "rounded",
    "pollinators": ["bees", "butterflies"],
    "wildlifeValue": ["birds"],
    "resistances": ["moderate-deer"],
    "commonSizes": [],
    "designUses": ["specimen", "accent", "border"],
    "notes": "Native; early pollinator resource. A beloved native tree with early pink blooms that appear before the foliage."
  },
  {
    "commonName": "Ruby Falls Redbud",
    "scientificName": "Cercis canadensis",
    "genus": "Cercis",
    "species": "canadensis",
    "cultivar": "Ruby Falls",
    "plantType": "tree",
    "category": "native",
    "tags": ["weeping", "burgundy-foliage", "compact", "dwarf"],
    "matureHeightMin": 6,
    "matureHeightMax": 8,
    "matureSpreadMin": 5,
    "matureSpreadMax": 6,
    "growthRate": "slow",
    "sunExposure": ["full-sun", "part-shade"],
    "waterNeeds": "moderate",
    "soilType": ["loam", "well-drained"],
    "evergreenOrDecid": "deciduous",
    "flowerColor": ["purple-pink"],
    "foliageColor": ["burgundy"],
    "fallColor": ["yellow"],
    "bloomSeason": ["early-spring"],
    "form": "weeping",
    "pollinators": ["bees", "butterflies"],
    "wildlifeValue": [],
    "resistances": ["moderate-deer"],
    "commonSizes": [],
    "designUses": ["specimen", "accent", "container"],
    "notes": "Deep burgundy foliage. A compact weeping redbud with cascading branches and rich burgundy foliage."
  },
  {
    "commonName": "Flame Thrower Redbud",
    "scientificName": "Cercis canadensis",
    "genus": "Cercis",
    "species": "canadensis",
    "cultivar": "NC2016-2",
    "trademark": "Flame Thrower速",
    "plantType": "tree",
    "category": "native",
    "tags": ["multicolor-foliage", "spring-blooming", "rainbow-effect"],
    "matureHeightMin": 15,
    "matureHeightMax": 20,
    "matureSpreadMin": 12,
    "matureSpreadMax": 15,
    "growthRate": "moderate",
    "sunExposure": ["full-sun", "part-shade"],
    "waterNeeds": "moderate",
    "soilType": ["loam", "well-drained"],
    "evergreenOrDecid": "deciduous",
    "flowerColor": ["pink"],
    "foliageColor": ["red", "orange", "yellow", "green"],
    "fallColor": ["yellow"],
    "bloomSeason": ["early-spring"],
    "form": "rounded",
    "pollinators": ["bees", "butterflies"],
    "wildlifeValue": [],
    "resistances": ["moderate-deer"],
    "commonSizes": [],
    "designUses": ["specimen", "accent"],
    "notes": "Multicolored foliage: red, orange, yellow, and green. A spectacular redbud with constantly changing foliage colors, creating a rainbow effect through the season."
  },
  {
    "commonName": "Hearts A' Fire Redbud",
    "scientificName": "Cercis canadensis",
    "genus": "Cercis",
    "species": "canadensis",
    "cultivar": "Hearts A' Fire",
    "plantType": "tree",
    "category": "native",
    "tags": ["red-new-growth", "spring-blooming", "colorful-foliage"],
    "matureHeightMin": 12,
    "matureHeightMax": 15,
    "matureSpreadMin": 10,
    "matureSpreadMax": 12,
    "growthRate": "moderate",
    "sunExposure": ["full-sun", "part-shade"],
    "waterNeeds": "moderate",
    "soilType": ["loam", "well-drained"],
    "evergreenOrDecid": "deciduous",
    "flowerColor": ["pink"],
    "foliageColor": ["red", "green"],
    "fallColor": ["yellow"],
    "bloomSeason": ["early-spring"],
    "form": "rounded",
    "pollinators": ["bees", "butterflies"],
    "wildlifeValue": [],
    "resistances": ["moderate-deer"],
    "commonSizes": [],
    "designUses": ["specimen", "accent"],
    "notes": "Bright red new growth. A colorful redbud with vivid red new foliage that matures to deep green."
  },
  {
    "commonName": "Garden Gems Amethyst Redbud",
    "scientificName": "Cercis canadensis",
    "genus": "Cercis",
    "species": "canadensis",
    "cultivar": "Garden Gems Amethyst",
    "plantType": "tree",
    "category": "native",
    "tags": ["compact", "dwarf-series", "spring-blooming"],
    "matureHeightMin": 10,
    "matureHeightMax": 12,
    "matureSpreadMin": 8,
    "matureSpreadMax": 10,
    "growthRate": "slow",
    "sunExposure": ["full-sun", "part-shade"],
    "waterNeeds": "moderate",
    "soilType": ["loam", "well-drained"],
    "evergreenOrDecid": "deciduous",
    "flowerColor": ["pink-purple"],
    "foliageColor": ["green"],
    "fallColor": ["yellow"],
    "bloomSeason": ["early-spring"],
    "form": "compact, rounded",
    "pollinators": ["bees", "butterflies"],
    "wildlifeValue": [],
    "resistances": ["moderate-deer"],
    "commonSizes": [],
    "designUses": ["specimen", "accent", "container"],
    "notes": "Part of the Garden Gems dwarf series. A compact redbud with vibrant pink-purple blooms and a tidy, rounded habit ideal for small landscapes."
  },
  {
    "commonName": "Green Machine Redbud",
    "scientificName": "Cercis canadensis",
    "genus": "Cercis",
    "species": "canadensis",
    "cultivar": "Green Machine",
    "plantType": "tree",
    "category": "native",
    "tags": ["vigorous", "bright-foliage", "spring-blooming"],
    "matureHeightMin": 12,
    "matureHeightMax": 15,
    "matureSpreadMin": 10,
    "matureSpreadMax": 12,
    "growthRate": "fast",
    "sunExposure": ["full-sun", "part-shade"],
    "waterNeeds": "moderate",
    "soilType": ["loam", "well-drained"],
    "evergreenOrDecid": "deciduous",
    "flowerColor": ["pink"],
    "foliageColor": ["bright-green"],
    "fallColor": ["yellow"],
    "bloomSeason": ["early-spring"],
    "form": "rounded",
    "pollinators": ["bees", "butterflies"],
    "wildlifeValue": [],
    "resistances": ["moderate-deer", "drought-moderate"],
    "commonSizes": [],
    "designUses": ["specimen", "accent"],
    "notes": "Bright green foliage; vigorous grower. A vigorous redbud with clean, bright green foliage and classic pink spring blooms."
  },
  {
    "commonName": "Garden Gems Emerald Redbud",
    "scientificName": "Cercis canadensis",
    "genus": "Cercis",
    "species": "canadensis",
    "cultivar": "Garden Gems Emerald",
    "plantType": "tree",
    "category": "native",
    "tags": ["dwarf", "compact", "dwarf-series", "spring-blooming"],
    "matureHeightMin": 8,
    "matureHeightMax": 10,
    "matureSpreadMin": 6,
    "matureSpreadMax": 8,
    "growthRate": "slow",
    "sunExposure": ["full-sun", "part-shade"],
    "waterNeeds": "moderate",
    "soilType": ["loam", "well-drained"],
    "evergreenOrDecid": "deciduous",
    "flowerColor": ["pink"],
    "foliageColor": ["green"],
    "fallColor": ["yellow"],
    "bloomSeason": ["early-spring"],
    "form": "compact, rounded",
    "pollinators": ["bees", "butterflies"],
    "wildlifeValue": [],
    "resistances": ["moderate-deer"],
    "commonSizes": [],
    "designUses": ["specimen", "accent", "container"],
    "notes": "Dwarf habit; excellent for small gardens. A dwarf redbud with a compact form and bright pink blooms, perfect for tight spaces."
  },
  {
    "commonName": "Golden Falls Redbud",
    "scientificName": "Cercis canadensis",
    "genus": "Cercis",
    "species": "canadensis",
    "cultivar": "Golden Falls",
    "plantType": "tree",
    "category": "native",
    "tags": ["columnar", "weeping", "golden-foliage", "narrow"],
    "matureHeightMin": 10,
    "matureHeightMax": 12,
    "matureSpreadMin": 3,
    "matureSpreadMax": 4,
    "growthRate": "slow",
    "sunExposure": ["full-sun", "part-shade"],
    "waterNeeds": "moderate",
    "soilType": ["loam", "well-drained"],
    "evergreenOrDecid": "deciduous",
    "flowerColor": ["pink"],
    "foliageColor": ["golden"],
    "fallColor": ["yellow"],
    "bloomSeason": ["early-spring"],
    "form": "columnar, weeping",
    "pollinators": ["bees", "butterflies"],
    "wildlifeValue": [],
    "resistances": ["moderate-deer"],
    "commonSizes": [],
    "designUses": ["specimen", "accent", "container"],
    "notes": "Golden foliage; extremely narrow habit. A striking columnar redbud with golden foliage and a narrow, cascading form ideal for tight vertical spaces."
  },
  {
    "commonName": "Carolina Sweetheart Redbud",
    "scientificName": "Cercis canadensis",
    "genus": "Cercis",
    "species": "canadensis",
    "cultivar": "NCCC1",
    "trademark": "Carolina Sweetheart速",
    "plantType": "tree",
    "category": "native",
    "tags": ["variegated-foliage", "multicolor", "spring-blooming", "showy"],
    "matureHeightMin": 20,
    "matureHeightMax": 25,
    "matureSpreadMin": 15,
    "matureSpreadMax": 20,
    "growthRate": "moderate",
    "sunExposure": ["full-sun", "part-shade"],
    "waterNeeds": "moderate",
    "soilType": ["loam", "well-drained"],
    "evergreenOrDecid": "deciduous",
    "flowerColor": ["pink"],
    "foliageColor": ["pink", "white", "burgundy", "green"],
    "fallColor": ["yellow"],
    "bloomSeason": ["early-spring"],
    "form": "rounded",
    "pollinators": ["bees", "butterflies"],
    "wildlifeValue": [],
    "resistances": ["moderate-deer"],
    "commonSizes": [],
    "designUses": ["specimen", "accent"],
    "notes": "Multicolored foliage: pink, white, burgundy, and green. A showy redbud with stunning variegated foliage that shifts through pink, burgundy, and green tones."
  },
  {
    "commonName": "Forest Pansy Redbud",
    "scientificName": "Cercis canadensis",
    "genus": "Cercis",
    "species": "canadensis",
    "cultivar": "Forest Pansy",
    "plantType": "tree",
    "category": "native",
    "tags": ["purple-foliage", "spring-blooming", "classic"],
    "matureHeightMin": 20,
    "matureHeightMax": 25,
    "matureSpreadMin": 20,
    "matureSpreadMax": 25,
    "growthRate": "moderate",
    "sunExposure": ["full-sun", "part-shade"],
    "waterNeeds": "moderate",
    "soilType": ["loam", "well-drained"],
    "evergreenOrDecid": "deciduous",
    "flowerColor": ["rosy-pink"],
    "foliageColor": ["burgundy", "purple"],
    "fallColor": ["yellow"],
    "bloomSeason": ["early-spring"],
    "form": "rounded",
    "pollinators": ["bees", "butterflies"],
    "wildlifeValue": [],
    "resistances": ["moderate-deer"],
    "commonSizes": [],
    "designUses": ["specimen", "accent"],
    "notes": "Deep purple foliage in spring. A classic purple-leaf redbud with rich burgundy foliage and abundant rosy-pink blooms."
  },
  {
    "commonName": "Mariken Ginkgo",
    "scientificName": "Ginkgo biloba",
    "genus": "Ginkgo",
    "species": "biloba",
    "cultivar": "Mariken",
    "plantType": "tree",
    "category": "ornamental",
    "tags": ["dwarf", "compact", "fall-color", "slow-growing"],
    "matureHeightMin": 2,
    "matureHeightMax": 3,
    "matureSpreadMin": 3,
    "matureSpreadMax": 4,
    "growthRate": "slow",
    "sunExposure": ["full-sun"],
    "waterNeeds": "low",
    "soilType": ["loam", "well-drained"],
    "evergreenOrDecid": "deciduous",
    "flowerColor": [],
    "foliageColor": ["green"],
    "fallColor": ["golden"],
    "bloomSeason": [],
    "form": "compact, rounded",
    "pollinators": [],
    "wildlifeValue": [],
    "resistances": ["deer", "drought"],
    "commonSizes": [],
    "designUses": ["container", "accent", "foundation"],
    "notes": "Slow-growing dwarf form. A miniature ginkgo with dense branching and bright golden fall color, ideal for small spaces or containers."
  },
  {
    "commonName": "Autumn Gold Ginkgo",
    "scientificName": "Ginkgo biloba",
    "genus": "Ginkgo",
    "species": "biloba",
    "cultivar": "Autumn Gold",
    "plantType": "tree",
    "category": "ornamental",
    "tags": ["male-selection", "fall-color", "symmetrical"],
    "matureHeightMin": 40,
    "matureHeightMax": 50,
    "matureSpreadMin": 30,
    "matureSpreadMax": 40,
    "growthRate": "slow",
    "sunExposure": ["full-sun"],
    "waterNeeds": "low",
    "soilType": ["loam", "well-drained"],
    "evergreenOrDecid": "deciduous",
    "flowerColor": [],
    "foliageColor": ["green"],
    "fallColor": ["golden"],
    "bloomSeason": [],
    "form": "broadly pyramidal",
    "pollinators": [],
    "wildlifeValue": [],
    "resistances": ["deer", "drought"],
    "commonSizes": [],
    "designUses": ["shade", "specimen"],
    "notes": "Male selection; brilliant fall color. A stately male ginkgo known for its symmetrical form and intense golden fall foliage."
  },
  {
    "commonName": "Chinese Pistache",
    "scientificName": "Pistacia chinensis",
    "genus": "Pistacia",
    "species": "chinensis",
    "cultivar": null,
    "plantType": "tree",
    "category": "ornamental",
    "tags": ["heat-tolerant", "drought-tolerant", "fall-color"],
    "matureHeightMin": 30,
    "matureHeightMax": 40,
    "matureSpreadMin": 20,
    "matureSpreadMax": 30,
    "growthRate": "moderate",
    "sunExposure": ["full-sun"],
    "waterNeeds": "low",
    "soilType": ["loam", "clay", "well-drained"],
    "evergreenOrDecid": "deciduous",
    "flowerColor": [],
    "foliageColor": ["green"],
    "fallColor": ["orange", "red"],
    "bloomSeason": [],
    "form": "rounded, spreading",
    "pollinators": [],
    "wildlifeValue": ["birds"],
    "resistances": ["deer", "drought", "heat"],
    "commonSizes": [],
    "designUses": ["shade", "specimen"],
    "notes": "Exceptional fall color; heat tolerant. A tough, drought-tolerant tree prized for its brilliant orange-red fall foliage."
  },
  {
    "commonName": "Moonglow Sweetbay Magnolia",
    "scientificName": "Magnolia virginiana",
    "genus": "Magnolia",
    "species": "virginiana",
    "cultivar": "Moonglow",
    "plantType": "tree",
    "category": "native",
    "tags": ["fragrant", "evergreen", "multi-stem", "wet-soil-tolerant"],
    "matureHeightMin": 20,
    "matureHeightMax": 30,
    "matureSpreadMin": 10,
    "matureSpreadMax": 15,
    "growthRate": "moderate",
    "sunExposure": ["full-sun", "part-shade"],
    "waterNeeds": "moderate",
    "soilType": ["loam", "moist", "acidic"],
    "evergreenOrDecid": "evergreen",
    "flowerColor": ["creamy-white"],
    "foliageColor": ["green"],
    "fallColor": [],
    "bloomSeason": ["late-spring", "summer"],
    "form": "upright, multi-stem",
    "pollinators": ["bees"],
    "wildlifeValue": ["birds"],
    "resistances": ["moderate-deer"],
    "commonSizes": [],
    "designUses": ["specimen", "screen", "accent"],
    "notes": "Semi-evergreen to evergreen in the South. A fragrant, semi-evergreen magnolia with upright multi-stem form and creamy white blooms."
  },
  {
    "commonName": "Jane Magnolia",
    "scientificName": "Magnolia hybrid",
    "genus": "Magnolia",
    "species": "hybrid",
    "cultivar": "Jane",
    "plantType": "tree",
    "category": "ornamental",
    "tags": ["late-blooming", "compact", "frost-resistant-bloom"],
    "matureHeightMin": 10,
    "matureHeightMax": 15,
    "matureSpreadMin": 8,
    "matureSpreadMax": 12,
    "growthRate": "slow",
    "sunExposure": ["full-sun", "part-shade"],
    "waterNeeds": "moderate",
    "soilType": ["loam", "well-drained", "acidic"],
    "evergreenOrDecid": "deciduous",
    "flowerColor": ["purple-red", "white"],
    "foliageColor": ["green"],
    "fallColor": ["yellow"],
    "bloomSeason": ["late-spring"],
    "form": "rounded",
    "pollinators": ["bees"],
    "wildlifeValue": [],
    "resistances": ["moderate-deer"],
    "commonSizes": [],
    "designUses": ["specimen", "accent", "foundation"],
    "notes": "Late blooming avoids frost damage. A compact magnolia with tulip-shaped purple-red blooms that open later than most magnolias."
  },
  {
    "commonName": "Ann Magnolia",
    "scientificName": "Magnolia hybrid",
    "genus": "Magnolia",
    "species": "hybrid",
    "cultivar": "Ann",
    "plantType": "tree",
    "category": "ornamental",
    "tags": ["compact", "late-blooming", "frost-resistant-bloom"],
    "matureHeightMin": 8,
    "matureHeightMax": 10,
    "matureSpreadMin": 8,
    "matureSpreadMax": 10,
    "growthRate": "slow",
    "sunExposure": ["full-sun", "part-shade"],
    "waterNeeds": "moderate",
    "soilType": ["loam", "well-drained", "acidic"],
    "evergreenOrDecid": "deciduous",
    "flowerColor": ["reddish-purple"],
    "foliageColor": ["green"],
    "fallColor": ["yellow"],
    "bloomSeason": ["late-spring"],
    "form": "rounded",
    "pollinators": ["bees"],
    "wildlifeValue": [],
    "resistances": ["moderate-deer"],
    "commonSizes": [],
    "designUses": ["specimen", "accent", "foundation", "container"],
    "notes": "Compact; late blooming. A small magnolia with deep reddish-purple blooms that appear later in spring, reducing frost risk."
  },
  {
    "commonName": "Centennial Blush Magnolia",
    "scientificName": "Magnolia stellata",
    "genus": "Magnolia",
    "species": "stellata",
    "cultivar": "Centennial Blush",
    "plantType": "tree",
    "category": "ornamental",
    "tags": ["star-magnolia", "heavy-bloomer", "spring-blooming"],
    "matureHeightMin": 12,
    "matureHeightMax": 18,
    "matureSpreadMin": 10,
    "matureSpreadMax": 15,
    "growthRate": "slow",
    "sunExposure": ["full-sun", "part-shade"],
    "waterNeeds": "moderate",
    "soilType": ["loam", "well-drained", "acidic"],
    "evergreenOrDecid": "deciduous",
    "flowerColor": ["pink"],
    "foliageColor": ["green"],
    "fallColor": ["yellow"],
    "bloomSeason": ["early-spring"],
    "form": "upright, oval",
    "pollinators": ["bees"],
    "wildlifeValue": [],
    "resistances": ["moderate-deer"],
    "commonSizes": [],
    "designUses": ["specimen", "accent"],
    "notes": "Heavy bloomer. A prolific blooming star magnolia with soft pink flowers that cover the branches in early spring."
  },
  {
    "commonName": "Judy Zuk Magnolia",
    "scientificName": "Magnolia hybrid",
    "genus": "Magnolia",
    "species": "hybrid",
    "cultivar": "Judy Zuk",
    "plantType": "tree",
    "category": "ornamental",
    "tags": ["yellow-flower", "rare", "spring-blooming"],
    "matureHeightMin": 20,
    "matureHeightMax": 25,
    "matureSpreadMin": 10,
    "matureSpreadMax": 15,
    "growthRate": "moderate",
    "sunExposure": ["full-sun", "part-shade"],
    "waterNeeds": "moderate",
    "soilType": ["loam", "well-drained", "acidic"],
    "evergreenOrDecid": "deciduous",
    "flowerColor": ["yellow", "orange"],
    "foliageColor": ["green"],
    "fallColor": ["yellow"],
    "bloomSeason": ["spring"],
    "form": "upright, pyramidal",
    "pollinators": ["bees"],
    "wildlifeValue": [],
    "resistances": ["moderate-deer"],
    "commonSizes": [],
    "designUses": ["specimen", "accent"],
    "notes": "Rare yellow magnolia. A striking magnolia with yellow-orange blooms and a narrow, upright form."
  },
  {
    "commonName": "Debonair Bald Cypress",
    "scientificName": "Taxodium distichum",
    "genus": "Taxodium",
    "species": "distichum",
    "cultivar": "Debonair",
    "plantType": "tree",
    "category": "native",
    "tags": ["adaptable", "wet-soil-tolerant", "drought-tolerant", "feathery-foliage"],
    "matureHeightMin": 40,
    "matureHeightMax": 50,
    "matureSpreadMin": 20,
    "matureSpreadMax": 30,
    "growthRate": "moderate",
    "sunExposure": ["full-sun"],
    "waterNeeds": "moderate",
    "soilType": ["loam", "clay", "moist", "well-drained"],
    "evergreenOrDecid": "deciduous",
    "flowerColor": [],
    "foliageColor": ["green"],
    "fallColor": ["copper", "orange"],
    "bloomSeason": [],
    "form": "pyramidal",
    "pollinators": [],
    "wildlifeValue": ["birds"],
    "resistances": ["deer", "drought"],
    "commonSizes": [],
    "designUses": ["shade", "specimen"],
    "notes": "Tolerates wet or dry soils. A refined bald cypress with soft, feathery foliage and excellent adaptability to wet or dry conditions."
  },
  {
    "commonName": "Fragrant Fountain Japanese Snowbell",
    "scientificName": "Styrax japonicus",
    "genus": "Styrax",
    "species": "japonicus",
    "cultivar": "Fragrant Fountain",
    "plantType": "tree",
    "category": "ornamental",
    "tags": ["weeping", "fragrant", "compact", "dwarf"],
    "matureHeightMin": 6,
    "matureHeightMax": 8,
    "matureSpreadMin": 4,
    "matureSpreadMax": 6,
    "growthRate": "slow",
    "sunExposure": ["full-sun", "part-shade"],
    "waterNeeds": "moderate",
    "soilType": ["loam", "well-drained", "acidic"],
    "evergreenOrDecid": "deciduous",
    "flowerColor": ["white"],
    "foliageColor": ["green"],
    "fallColor": ["yellow"],
    "bloomSeason": ["late-spring"],
    "form": "weeping",
    "pollinators": ["bees"],
    "wildlifeValue": [],
    "resistances": ["moderate-deer"],
    "commonSizes": [],
    "designUses": ["specimen", "accent", "container"],
    "notes": "Highly fragrant blooms. A compact weeping snowbell with cascading branches and intensely fragrant white flowers."
  },
  {
    "commonName": "Marley's Pink Parasol Styrax",
    "scientificName": "Styrax japonicus",
    "genus": "Styrax",
    "species": "japonicus",
    "cultivar": "Marley's Pink Parasol",
    "plantType": "tree",
    "category": "ornamental",
    "tags": ["pink-flower", "rare", "bell-shaped-bloom"],
    "matureHeightMin": 8,
    "matureHeightMax": 10,
    "matureSpreadMin": 6,
    "matureSpreadMax": 8,
    "growthRate": "slow",
    "sunExposure": ["full-sun", "part-shade"],
    "waterNeeds": "moderate",
    "soilType": ["loam", "well-drained", "acidic"],
    "evergreenOrDecid": "deciduous",
    "flowerColor": ["pink"],
    "foliageColor": ["green"],
    "fallColor": ["yellow"],
    "bloomSeason": ["late-spring"],
    "form": "rounded",
    "pollinators": ["bees"],
    "wildlifeValue": [],
    "resistances": ["moderate-deer"],
    "commonSizes": [],
    "designUses": ["specimen", "accent"],
    "notes": "Rare pink-flowering snowbell. A charming snowbell with soft pink bell-shaped blooms that hang delicately from the branches."
  },
  {
    "commonName": "Evening Light Styrax",
    "scientificName": "Styrax japonicus",
    "genus": "Styrax",
    "species": "japonicus",
    "cultivar": "Evening Light",
    "plantType": "tree",
    "category": "ornamental",
    "tags": ["purple-foliage", "contrast", "bell-shaped-bloom"],
    "matureHeightMin": 8,
    "matureHeightMax": 10,
    "matureSpreadMin": 6,
    "matureSpreadMax": 8,
    "growthRate": "slow",
    "sunExposure": ["full-sun", "part-shade"],
    "waterNeeds": "moderate",
    "soilType": ["loam", "well-drained", "acidic"],
    "evergreenOrDecid": "deciduous",
    "flowerColor": ["white"],
    "foliageColor": ["purple"],
    "fallColor": ["yellow"],
    "bloomSeason": ["late-spring"],
    "form": "rounded",
    "pollinators": ["bees"],
    "wildlifeValue": [],
    "resistances": ["moderate-deer"],
    "commonSizes": [],
    "designUses": ["specimen", "accent"],
    "notes": "Dark purple foliage. A dramatic snowbell with deep purple foliage that contrasts beautifully with its white bell-shaped blooms."
  },
  {
    "commonName": "Snowcone Styrax",
    "scientificName": "Styrax japonicus",
    "genus": "Styrax",
    "species": "japonicus",
    "cultivar": "Snowcone",
    "plantType": "tree",
    "category": "ornamental",
    "tags": ["heavy-bloomer", "compact", "bell-shaped-bloom"],
    "matureHeightMin": 12,
    "matureHeightMax": 15,
    "matureSpreadMin": 8,
    "matureSpreadMax": 10,
    "growthRate": "moderate",
    "sunExposure": ["full-sun", "part-shade"],
    "waterNeeds": "moderate",
    "soilType": ["loam", "well-drained", "acidic"],
    "evergreenOrDecid": "deciduous",
    "flowerColor": ["white"],
    "foliageColor": ["green"],
    "fallColor": ["yellow"],
    "bloomSeason": ["late-spring"],
    "form": "upright, oval",
    "pollinators": ["bees"],
    "wildlifeValue": [],
    "resistances": ["moderate-deer"],
    "commonSizes": [],
    "designUses": ["specimen", "accent", "border"],
    "notes": "Heavy bloomer. A compact snowbell with masses of white bell-shaped flowers that cover the branches in late spring."
  },
  {
    "commonName": "Nightfall Styrax",
    "scientificName": "Styrax japonicus",
    "genus": "Styrax",
    "species": "japonicus",
    "cultivar": "Nightfall",
    "plantType": "tree",
    "category": "ornamental",
    "tags": ["dark-foliage", "compact", "bell-shaped-bloom"],
    "matureHeightMin": 10,
    "matureHeightMax": 12,
    "matureSpreadMin": 6,
    "matureSpreadMax": 8,
    "growthRate": "slow",
    "sunExposure": ["full-sun", "part-shade"],
    "waterNeeds": "moderate",
    "soilType": ["loam", "well-drained", "acidic"],
    "evergreenOrDecid": "deciduous",
    "flowerColor": ["white"],
    "foliageColor": ["dark-green", "purple"],
    "fallColor": ["yellow"],
    "bloomSeason": ["late-spring"],
    "form": "upright, oval",
    "pollinators": ["bees"],
    "wildlifeValue": [],
    "resistances": ["moderate-deer"],
    "commonSizes": [],
    "designUses": ["specimen", "accent"],
    "notes": "Dark foliage; compact habit. A compact snowbell with dark foliage and abundant white blooms that contrast beautifully against the leaves."
  },
  {
    "commonName": "White Fringetree",
    "scientificName": "Chionanthus virginicus",
    "genus": "Chionanthus",
    "species": "virginicus",
    "cultivar": null,
    "plantType": "tree",
    "category": "native",
    "tags": ["native", "fragrant", "pollinator", "spring-blooming"],
    "matureHeightMin": 12,
    "matureHeightMax": 20,
    "matureSpreadMin": 10,
    "matureSpreadMax": 15,
    "growthRate": "slow",
    "sunExposure": ["full-sun", "part-shade"],
    "waterNeeds": "moderate",
    "soilType": ["loam", "well-drained", "moist"],
    "evergreenOrDecid": "deciduous",
    "flowerColor": ["white"],
    "foliageColor": ["green"],
    "fallColor": ["yellow"],
    "bloomSeason": ["late-spring"],
    "form": "rounded",
    "pollinators": ["bees", "butterflies"],
    "wildlifeValue": ["birds"],
    "resistances": ["deer"],
    "commonSizes": [],
    "designUses": ["specimen", "accent", "border"],
    "notes": "Native; highly fragrant blooms. A native tree with clouds of fragrant white fringe-like flowers that appear in late spring."
  },
  {
    "commonName": "Alabama Beauty Camellia",
    "scientificName": "Camellia sasanqua",
    "genus": "Camellia",
    "species": "sasanqua",
    "cultivar": "Alabama Beauty",
    "plantType": "shrub",
    "category": "ornamental",
    "tags": ["fall-blooming", "evergreen", "sun-tolerant"],
    "matureHeightMin": 8,
    "matureHeightMax": 12,
    "matureSpreadMin": 6,
    "matureSpreadMax": 8,
    "growthRate": "moderate",
    "sunExposure": ["full-sun", "part-shade"],
    "waterNeeds": "moderate",
    "soilType": ["loam", "well-drained", "acidic"],
    "evergreenOrDecid": "evergreen",
    "flowerColor": ["white"],
    "foliageColor": ["dark-green"],
    "fallColor": [],
    "bloomSeason": ["fall"],
    "form": "upright",
    "pollinators": ["bees"],
    "wildlifeValue": [],
    "resistances": ["deer"],
    "commonSizes": [],
    "designUses": ["screen", "hedge", "specimen", "foundation"],
    "notes": "Large white single flowers in fall. A vigorous sasanqua with clean white blooms and an upright habit."
  },
  {
    "commonName": "Shishi Gashira Camellia",
    "scientificName": "Camellia hiemalis",
    "genus": "Camellia",
    "species": "hiemalis",
    "cultivar": "Shishi Gashira",
    "plantType": "shrub",
    "category": "ornamental",
    "tags": ["fall-blooming", "evergreen", "compact", "sasanqua-type"],
    "matureHeightMin": 3,
    "matureHeightMax": 5,
    "matureSpreadMin": 4,
    "matureSpreadMax": 6,
    "growthRate": "slow",
    "sunExposure": ["full-sun", "part-shade"],
    "waterNeeds": "moderate",
    "soilType": ["loam", "well-drained", "acidic"],
    "evergreenOrDecid": "evergreen",
    "flowerColor": ["rose-pink"],
    "foliageColor": ["dark-green"],
    "fallColor": [],
    "bloomSeason": ["fall", "winter"],
    "form": "compact, spreading",
    "pollinators": ["bees"],
    "wildlifeValue": [],
    "resistances": ["deer"],
    "commonSizes": [],
    "designUses": ["foundation", "border", "mass-planting", "container"],
    "notes": "Compact spreading habit; semi-double rose-pink flowers. One of the most popular low-growing camellias for foundation plantings."
  },
  {
    "commonName": "Yuletide Candle Camellia",
    "scientificName": "Camellia sasanqua",
    "genus": "Camellia",
    "species": "sasanqua",
    "cultivar": "Yuletide Candle",
    "plantType": "shrub",
    "category": "ornamental",
    "tags": ["fall-blooming", "evergreen", "columnar", "narrow"],
    "matureHeightMin": 8,
    "matureHeightMax": 10,
    "matureSpreadMin": 3,
    "matureSpreadMax": 4,
    "growthRate": "moderate",
    "sunExposure": ["full-sun", "part-shade"],
    "waterNeeds": "moderate",
    "soilType": ["loam", "well-drained", "acidic"],
    "evergreenOrDecid": "evergreen",
    "flowerColor": ["red"],
    "foliageColor": ["dark-green"],
    "fallColor": [],
    "bloomSeason": ["fall", "winter"],
    "form": "columnar, upright",
    "pollinators": ["bees"],
    "wildlifeValue": [],
    "resistances": ["deer"],
    "commonSizes": [],
    "designUses": ["screen", "accent", "hedge"],
    "notes": "Narrow upright form with red blooms and yellow stamens. A columnar sasanqua ideal for tight spaces and vertical accents."
  },
  {
    "commonName": "Autumn Rocket Camellia",
    "scientificName": "Camellia sasanqua",
    "genus": "Camellia",
    "species": "sasanqua",
    "cultivar": "Autumn Rocket",
    "plantType": "shrub",
    "category": "ornamental",
    "tags": ["fall-blooming", "evergreen", "columnar", "narrow"],
    "matureHeightMin": 8,
    "matureHeightMax": 12,
    "matureSpreadMin": 3,
    "matureSpreadMax": 5,
    "growthRate": "moderate",
    "sunExposure": ["full-sun", "part-shade"],
    "waterNeeds": "moderate",
    "soilType": ["loam", "well-drained", "acidic"],
    "evergreenOrDecid": "evergreen",
    "flowerColor": ["white", "pink"],
    "foliageColor": ["dark-green"],
    "fallColor": [],
    "bloomSeason": ["fall"],
    "form": "columnar, upright",
    "pollinators": ["bees"],
    "wildlifeValue": [],
    "resistances": ["deer"],
    "commonSizes": [],
    "designUses": ["screen", "accent", "hedge"],
    "notes": "Strongly upright, columnar habit. An excellent narrow sasanqua for screening and tight vertical plantings."
  },
  {
    "commonName": "Rose of Autumn Camellia",
    "scientificName": "Camellia sasanqua",
    "genus": "Camellia",
    "species": "sasanqua",
    "cultivar": "Rose of Autumn",
    "plantType": "shrub",
    "category": "ornamental",
    "tags": ["fall-blooming", "evergreen"],
    "matureHeightMin": 6,
    "matureHeightMax": 10,
    "matureSpreadMin": 5,
    "matureSpreadMax": 8,
    "growthRate": "moderate",
    "sunExposure": ["full-sun", "part-shade"],
    "waterNeeds": "moderate",
    "soilType": ["loam", "well-drained", "acidic"],
    "evergreenOrDecid": "evergreen",
    "flowerColor": ["pink"],
    "foliageColor": ["dark-green"],
    "fallColor": [],
    "bloomSeason": ["fall"],
    "form": "upright, spreading",
    "pollinators": ["bees"],
    "wildlifeValue": [],
    "resistances": ["deer"],
    "commonSizes": [],
    "designUses": ["specimen", "border", "foundation"],
    "notes": "Soft pink fall blooms. A graceful sasanqua with abundant pink flowers in autumn."
  },
  {
    "commonName": "October Magic Ruby Camellia",
    "scientificName": "Camellia sasanqua",
    "genus": "Camellia",
    "species": "sasanqua",
    "cultivar": "October Magic Ruby",
    "plantType": "shrub",
    "category": "ornamental",
    "tags": ["fall-blooming", "evergreen", "compact", "october-magic-series"],
    "matureHeightMin": 3,
    "matureHeightMax": 5,
    "matureSpreadMin": 3,
    "matureSpreadMax": 5,
    "growthRate": "slow",
    "sunExposure": ["full-sun", "part-shade"],
    "waterNeeds": "moderate",
    "soilType": ["loam", "well-drained", "acidic"],
    "evergreenOrDecid": "evergreen",
    "flowerColor": ["red"],
    "foliageColor": ["dark-green"],
    "fallColor": [],
    "bloomSeason": ["fall"],
    "form": "compact, rounded",
    "pollinators": ["bees"],
    "wildlifeValue": [],
    "resistances": ["deer"],
    "commonSizes": [],
    "designUses": ["foundation", "border", "mass-planting", "container"],
    "notes": "Part of the October Magic速 series. A compact sasanqua with rich red blooms, ideal for small spaces."
  },
  {
    "commonName": "Hot Flash Camellia",
    "scientificName": "Camellia sasanqua",
    "genus": "Camellia",
    "species": "sasanqua",
    "cultivar": "Hot Flash",
    "plantType": "shrub",
    "category": "ornamental",
    "tags": ["fall-blooming", "evergreen", "vivid-color"],
    "matureHeightMin": 6,
    "matureHeightMax": 10,
    "matureSpreadMin": 5,
    "matureSpreadMax": 8,
    "growthRate": "moderate",
    "sunExposure": ["full-sun", "part-shade"],
    "waterNeeds": "moderate",
    "soilType": ["loam", "well-drained", "acidic"],
    "evergreenOrDecid": "evergreen",
    "flowerColor": ["red", "pink"],
    "foliageColor": ["dark-green"],
    "fallColor": [],
    "bloomSeason": ["fall"],
    "form": "upright",
    "pollinators": ["bees"],
    "wildlifeValue": [],
    "resistances": ["deer"],
    "commonSizes": [],
    "designUses": ["specimen", "screen", "foundation"],
    "notes": "Vivid pink-red blooms. A vigorous sasanqua with eye-catching fall flowers."
  },
  {
    "commonName": "Sparkling Burgundy Camellia",
    "scientificName": "Camellia sasanqua",
    "genus": "Camellia",
    "species": "sasanqua",
    "cultivar": "Sparkling Burgundy",
    "plantType": "shrub",
    "category": "ornamental",
    "tags": ["fall-blooming", "evergreen", "peony-form"],
    "matureHeightMin": 8,
    "matureHeightMax": 12,
    "matureSpreadMin": 6,
    "matureSpreadMax": 8,
    "growthRate": "moderate",
    "sunExposure": ["full-sun", "part-shade"],
    "waterNeeds": "moderate",
    "soilType": ["loam", "well-drained", "acidic"],
    "evergreenOrDecid": "evergreen",
    "flowerColor": ["ruby-pink", "burgundy"],
    "foliageColor": ["dark-green"],
    "fallColor": [],
    "bloomSeason": ["fall"],
    "form": "upright",
    "pollinators": ["bees"],
    "wildlifeValue": [],
    "resistances": ["deer"],
    "commonSizes": [],
    "designUses": ["specimen", "screen", "hedge"],
    "notes": "Deep ruby-pink peony-form blooms. A vigorous, upright sasanqua with rich burgundy-toned flowers."
  },
  {
    "commonName": "Japanese Fantasy Camellia",
    "scientificName": "Camellia sasanqua",
    "genus": "Camellia",
    "species": "sasanqua",
    "cultivar": "Japanese Fantasy",
    "plantType": "shrub",
    "category": "ornamental",
    "tags": ["fall-blooming", "evergreen"],
    "matureHeightMin": 6,
    "matureHeightMax": 10,
    "matureSpreadMin": 5,
    "matureSpreadMax": 8,
    "growthRate": "moderate",
    "sunExposure": ["full-sun", "part-shade"],
    "waterNeeds": "moderate",
    "soilType": ["loam", "well-drained", "acidic"],
    "evergreenOrDecid": "evergreen",
    "flowerColor": ["pink"],
    "foliageColor": ["dark-green"],
    "fallColor": [],
    "bloomSeason": ["fall"],
    "form": "upright, spreading",
    "pollinators": ["bees"],
    "wildlifeValue": [],
    "resistances": ["deer"],
    "commonSizes": [],
    "designUses": ["specimen", "screen", "border"],
    "notes": "Delicate pink blooms in fall. A graceful sasanqua with abundant flowering and an elegant habit."
  },
  {
    "commonName": "Our Linda Camellia",
    "scientificName": "Camellia sasanqua",
    "genus": "Camellia",
    "species": "sasanqua",
    "cultivar": "Our Linda",
    "plantType": "shrub",
    "category": "ornamental",
    "tags": ["fall-blooming", "evergreen"],
    "matureHeightMin": 6,
    "matureHeightMax": 10,
    "matureSpreadMin": 5,
    "matureSpreadMax": 8,
    "growthRate": "moderate",
    "sunExposure": ["full-sun", "part-shade"],
    "waterNeeds": "moderate",
    "soilType": ["loam", "well-drained", "acidic"],
    "evergreenOrDecid": "evergreen",
    "flowerColor": ["pink"],
    "foliageColor": ["dark-green"],
    "fallColor": [],
    "bloomSeason": ["fall"],
    "form": "upright",
    "pollinators": ["bees"],
    "wildlifeValue": [],
    "resistances": ["deer"],
    "commonSizes": [],
    "designUses": ["specimen", "foundation", "border"],
    "notes": "Pink fall blooms. A reliable sasanqua with a tidy upright habit."
  },
  {
    "commonName": "Egao Corkscrew Camellia",
    "scientificName": "Camellia sasanqua",
    "genus": "Camellia",
    "species": "sasanqua",
    "cultivar": "Egao Corkscrew",
    "plantType": "shrub",
    "category": "ornamental",
    "tags": ["fall-blooming", "evergreen", "contorted-branches", "architectural"],
    "matureHeightMin": 6,
    "matureHeightMax": 10,
    "matureSpreadMin": 4,
    "matureSpreadMax": 6,
    "growthRate": "slow",
    "sunExposure": ["full-sun", "part-shade"],
    "waterNeeds": "moderate",
    "soilType": ["loam", "well-drained", "acidic"],
    "evergreenOrDecid": "evergreen",
    "flowerColor": ["pink"],
    "foliageColor": ["dark-green"],
    "fallColor": [],
    "bloomSeason": ["fall"],
    "form": "upright, contorted",
    "pollinators": ["bees"],
    "wildlifeValue": [],
    "resistances": ["deer"],
    "commonSizes": [],
    "designUses": ["specimen", "accent"],
    "notes": "Contorted/twisted branching adds winter interest. A unique sasanqua with corkscrew branches and pink fall blooms."
  },
  {
    "commonName": "Winter's Joy Camellia",
    "scientificName": "Camellia hiemalis",
    "genus": "Camellia",
    "species": "hiemalis",
    "cultivar": "Winter's Joy",
    "plantType": "shrub",
    "category": "ornamental",
    "tags": ["fall-blooming", "winter-blooming", "evergreen", "sasanqua-type"],
    "matureHeightMin": 6,
    "matureHeightMax": 10,
    "matureSpreadMin": 5,
    "matureSpreadMax": 8,
    "growthRate": "moderate",
    "sunExposure": ["full-sun", "part-shade"],
    "waterNeeds": "moderate",
    "soilType": ["loam", "well-drained", "acidic"],
    "evergreenOrDecid": "evergreen",
    "flowerColor": ["pink", "white"],
    "foliageColor": ["dark-green"],
    "fallColor": [],
    "bloomSeason": ["fall", "winter"],
    "form": "upright",
    "pollinators": ["bees"],
    "wildlifeValue": [],
    "resistances": ["deer"],
    "commonSizes": [],
    "designUses": ["specimen", "screen", "foundation"],
    "notes": "Extended bloom from late fall into early winter. A sasanqua-type camellia that bridges fall and winter bloom seasons."
  },
  {
    "commonName": "Cotton Candy Camellia",
    "scientificName": "Camellia sasanqua",
    "genus": "Camellia",
    "species": "sasanqua",
    "cultivar": "Cotton Candy",
    "plantType": "shrub",
    "category": "ornamental",
    "tags": ["fall-blooming", "evergreen", "soft-color"],
    "matureHeightMin": 6,
    "matureHeightMax": 10,
    "matureSpreadMin": 5,
    "matureSpreadMax": 8,
    "growthRate": "moderate",
    "sunExposure": ["full-sun", "part-shade"],
    "waterNeeds": "moderate",
    "soilType": ["loam", "well-drained", "acidic"],
    "evergreenOrDecid": "evergreen",
    "flowerColor": ["soft-pink"],
    "foliageColor": ["dark-green"],
    "fallColor": [],
    "bloomSeason": ["fall"],
    "form": "upright, spreading",
    "pollinators": ["bees"],
    "wildlifeValue": [],
    "resistances": ["deer"],
    "commonSizes": [],
    "designUses": ["specimen", "foundation", "border"],
    "notes": "Soft pink blooms. A charming sasanqua with delicate pink flowers and a graceful habit."
  },
  {
    "commonName": "High Fragrance Camellia",
    "scientificName": "Camellia japonica x lutchuensis",
    "genus": "Camellia",
    "species": "japonica x lutchuensis",
    "cultivar": "High Fragrance",
    "plantType": "shrub",
    "category": "ornamental",
    "tags": ["japonica", "hybrid", "fragrant", "winter-blooming", "evergreen"],
    "matureHeightMin": 8,
    "matureHeightMax": 12,
    "matureSpreadMin": 6,
    "matureSpreadMax": 8,
    "growthRate": "moderate",
    "sunExposure": ["part-shade", "part-sun"],
    "waterNeeds": "moderate",
    "soilType": ["loam", "well-drained", "acidic"],
    "evergreenOrDecid": "evergreen",
    "flowerColor": ["pink", "ivory"],
    "foliageColor": ["dark-green"],
    "fallColor": [],
    "bloomSeason": ["winter", "early-spring"],
    "form": "upright",
    "pollinators": ["bees"],
    "wildlifeValue": [],
    "resistances": ["deer"],
    "commonSizes": [],
    "designUses": ["specimen", "accent", "foundation"],
    "notes": "Hybrid (japonica  lutchuensis). One of the most fragrant camellias available, with large peony-form blooms in ivory-pink."
  },
  {
    "commonName": "April Tryst Camellia",
    "scientificName": "Camellia japonica",
    "genus": "Camellia",
    "species": "japonica",
    "cultivar": "April Tryst",
    "plantType": "shrub",
    "category": "ornamental",
    "tags": ["japonica", "spring-blooming", "evergreen", "late-season"],
    "matureHeightMin": 6,
    "matureHeightMax": 10,
    "matureSpreadMin": 5,
    "matureSpreadMax": 8,
    "growthRate": "moderate",
    "sunExposure": ["part-shade", "part-sun"],
    "waterNeeds": "moderate",
    "soilType": ["loam", "well-drained", "acidic"],
    "evergreenOrDecid": "evergreen",
    "flowerColor": ["red"],
    "foliageColor": ["dark-green"],
    "fallColor": [],
    "bloomSeason": ["spring"],
    "form": "upright, compact",
    "pollinators": ["bees"],
    "wildlifeValue": [],
    "resistances": ["deer"],
    "commonSizes": [],
    "designUses": ["specimen", "accent", "foundation"],
    "notes": "Late-blooming japonica with red anemone-form flowers in March-April. Extends the camellia season into spring."
  },
  {
    "commonName": "Blood of China Camellia",
    "scientificName": "Camellia japonica",
    "genus": "Camellia",
    "species": "japonica",
    "cultivar": "Blood of China",
    "plantType": "shrub",
    "category": "ornamental",
    "tags": ["japonica", "winter-blooming", "evergreen", "late-season", "heirloom"],
    "matureHeightMin": 8,
    "matureHeightMax": 12,
    "matureSpreadMin": 6,
    "matureSpreadMax": 10,
    "growthRate": "moderate",
    "sunExposure": ["part-shade", "part-sun"],
    "waterNeeds": "moderate",
    "soilType": ["loam", "well-drained", "acidic"],
    "evergreenOrDecid": "evergreen",
    "flowerColor": ["deep-red"],
    "foliageColor": ["dark-green"],
    "fallColor": [],
    "bloomSeason": ["late-winter", "spring"],
    "form": "upright",
    "pollinators": ["bees"],
    "wildlifeValue": [],
    "resistances": ["deer"],
    "commonSizes": [],
    "designUses": ["specimen", "accent", "foundation"],
    "notes": "Deep red semi-double to peony-form blooms. A classic late-season japonica with rich crimson flowers."
  },
  {
    "commonName": "Greensboro Red Camellia",
    "scientificName": "Camellia japonica",
    "genus": "Camellia",
    "species": "japonica",
    "cultivar": "Greensboro Red",
    "plantType": "shrub",
    "category": "ornamental",
    "tags": ["japonica", "winter-blooming", "evergreen", "cold-hardy"],
    "matureHeightMin": 8,
    "matureHeightMax": 15,
    "matureSpreadMin": 6,
    "matureSpreadMax": 10,
    "growthRate": "moderate",
    "sunExposure": ["part-shade", "part-sun"],
    "waterNeeds": "moderate",
    "soilType": ["loam", "well-drained", "acidic"],
    "evergreenOrDecid": "evergreen",
    "flowerColor": ["red"],
    "foliageColor": ["dark-green"],
    "fallColor": [],
    "bloomSeason": ["winter", "early-spring"],
    "form": "upright",
    "pollinators": ["bees"],
    "wildlifeValue": [],
    "resistances": ["deer"],
    "commonSizes": [],
    "designUses": ["specimen", "accent", "screen"],
    "notes": "Red semi-double blooms. A vigorous, cold-hardy japonica with reliable red winter flowers."
  },
  {
    "commonName": "April Remembered Camellia",
    "scientificName": "Camellia japonica",
    "genus": "Camellia",
    "species": "japonica",
    "cultivar": "April Remembered",
    "plantType": "shrub",
    "category": "ornamental",
    "tags": ["japonica", "spring-blooming", "evergreen", "late-season"],
    "matureHeightMin": 6,
    "matureHeightMax": 10,
    "matureSpreadMin": 5,
    "matureSpreadMax": 8,
    "growthRate": "moderate",
    "sunExposure": ["part-shade", "part-sun"],
    "waterNeeds": "moderate",
    "soilType": ["loam", "well-drained", "acidic"],
    "evergreenOrDecid": "evergreen",
    "flowerColor": ["pink"],
    "foliageColor": ["dark-green"],
    "fallColor": [],
    "bloomSeason": ["spring"],
    "form": "upright, compact",
    "pollinators": ["bees"],
    "wildlifeValue": [],
    "resistances": ["deer"],
    "commonSizes": [],
    "designUses": ["specimen", "accent", "foundation"],
    "notes": "Late-blooming pink japonica. Extends the camellia season into mid-spring."
  },
  {
    "commonName": "Junior Miss Camellia",
    "scientificName": "Camellia japonica",
    "genus": "Camellia",
    "species": "japonica",
    "cultivar": "Junior Miss",
    "plantType": "shrub",
    "category": "ornamental",
    "tags": ["japonica", "winter-blooming", "evergreen"],
    "matureHeightMin": 8,
    "matureHeightMax": 12,
    "matureSpreadMin": 6,
    "matureSpreadMax": 8,
    "growthRate": "moderate",
    "sunExposure": ["part-shade", "part-sun"],
    "waterNeeds": "moderate",
    "soilType": ["loam", "well-drained", "acidic"],
    "evergreenOrDecid": "evergreen",
    "flowerColor": ["pink"],
    "foliageColor": ["dark-green"],
    "fallColor": [],
    "bloomSeason": ["winter", "early-spring"],
    "form": "upright",
    "pollinators": ["bees"],
    "wildlifeValue": [],
    "resistances": ["deer"],
    "commonSizes": [],
    "designUses": ["specimen", "accent", "foundation"],
    "notes": "Pink semi-double to peony-form blooms. A classic japonica with elegant pink flowers."
  },
  {
    "commonName": "White by the Gate Camellia",
    "scientificName": "Camellia japonica",
    "genus": "Camellia",
    "species": "japonica",
    "cultivar": "White by the Gate",
    "plantType": "shrub",
    "category": "ornamental",
    "tags": ["japonica", "winter-blooming", "evergreen", "white-flower"],
    "matureHeightMin": 8,
    "matureHeightMax": 12,
    "matureSpreadMin": 6,
    "matureSpreadMax": 8,
    "growthRate": "moderate",
    "sunExposure": ["part-shade", "part-sun"],
    "waterNeeds": "moderate",
    "soilType": ["loam", "well-drained", "acidic"],
    "evergreenOrDecid": "evergreen",
    "flowerColor": ["white"],
    "foliageColor": ["dark-green"],
    "fallColor": [],
    "bloomSeason": ["winter", "early-spring"],
    "form": "upright",
    "pollinators": ["bees"],
    "wildlifeValue": [],
    "resistances": ["deer"],
    "commonSizes": [],
    "designUses": ["specimen", "accent", "foundation"],
    "notes": "Pure white semi-double blooms. An elegant white japonica with a clean, classic look."
  },
  {
    "commonName": "Professor Sargent Camellia",
    "scientificName": "Camellia japonica",
    "genus": "Camellia",
    "species": "japonica",
    "cultivar": "Professor Sargent",
    "plantType": "shrub",
    "category": "ornamental",
    "tags": ["japonica", "winter-blooming", "evergreen", "heirloom"],
    "matureHeightMin": 8,
    "matureHeightMax": 12,
    "matureSpreadMin": 6,
    "matureSpreadMax": 10,
    "growthRate": "moderate",
    "sunExposure": ["part-shade", "part-sun"],
    "waterNeeds": "moderate",
    "soilType": ["loam", "well-drained", "acidic"],
    "evergreenOrDecid": "evergreen",
    "flowerColor": ["dark-red"],
    "foliageColor": ["dark-green"],
    "fallColor": [],
    "bloomSeason": ["winter", "early-spring"],
    "form": "upright, dense",
    "pollinators": ["bees"],
    "wildlifeValue": [],
    "resistances": ["deer"],
    "commonSizes": [],
    "designUses": ["specimen", "accent", "foundation", "screen"],
    "notes": "Dark red peony to anemone-form blooms. A classic heirloom japonica with dense, richly colored flowers."
  },
  {
    "commonName": "Anouk Supreme Spanish Lavender",
    "scientificName": "Lavandula stoechas",
    "genus": "Lavandula",
    "species": "stoechas",
    "cultivar": "Anouk Supreme",
    "plantType": "perennial",
    "category": "edible",
    "tags": ["herb", "fragrant", "pollinator", "drought-tolerant", "evergreen", "spanish-lavender"],
    "matureHeightMin": 1.5,
    "matureHeightMax": 2,
    "matureSpreadMin": 1.5,
    "matureSpreadMax": 2,
    "growthRate": "moderate",
    "sunExposure": ["full-sun"],
    "waterNeeds": "low",
    "soilType": ["well-drained", "sand", "loam"],
    "evergreenOrDecid": "evergreen",
    "flowerColor": ["purple"],
    "foliageColor": ["silver-green"],
    "fallColor": [],
    "bloomSeason": ["spring", "summer"],
    "form": "compact, rounded",
    "pollinators": ["bees", "butterflies"],
    "wildlifeValue": [],
    "resistances": ["deer", "rabbit", "drought"],
    "commonSizes": [],
    "designUses": ["border", "mass-planting", "container", "foundation"],
    "notes": "Showy butterfly-top blooms; compact habit. A prolific Spanish lavender with bold purple flowers and excellent heat tolerance."
  },
  {
    "commonName": "Primavera Lavender",
    "scientificName": "Lavandula stoechas",
    "genus": "Lavandula",
    "species": "stoechas",
    "cultivar": "Primavera",
    "plantType": "perennial",
    "category": "edible",
    "tags": ["herb", "fragrant", "pollinator", "drought-tolerant", "spanish-lavender"],
    "matureHeightMin": 1.5,
    "matureHeightMax": 2.5,
    "matureSpreadMin": 1.5,
    "matureSpreadMax": 2,
    "growthRate": "moderate",
    "sunExposure": ["full-sun"],
    "waterNeeds": "low",
    "soilType": ["well-drained", "sand", "loam"],
    "evergreenOrDecid": "evergreen",
    "flowerColor": ["purple"],
    "foliageColor": ["silver-green"],
    "fallColor": [],
    "bloomSeason": ["spring", "summer"],
    "form": "compact, rounded",
    "pollinators": ["bees", "butterflies"],
    "wildlifeValue": [],
    "resistances": ["deer", "rabbit", "drought"],
    "commonSizes": [],
    "designUses": ["border", "mass-planting", "container"],
    "notes": "Spanish-type lavender with showy blooms. A reliable, fragrant lavender for hot, sunny sites."
  },
  {
    "commonName": "Trailing Rosemary",
    "scientificName": "Salvia rosmarinus",
    "genus": "Salvia",
    "species": "rosmarinus",
    "cultivar": "Prostratus",
    "plantType": "perennial",
    "category": "edible",
    "tags": ["herb", "fragrant", "drought-tolerant", "evergreen", "groundcover", "trailing"],
    "matureHeightMin": 0.5,
    "matureHeightMax": 1,
    "matureSpreadMin": 3,
    "matureSpreadMax": 5,
    "growthRate": "moderate",
    "sunExposure": ["full-sun"],
    "waterNeeds": "low",
    "soilType": ["well-drained", "sand", "loam"],
    "evergreenOrDecid": "evergreen",
    "flowerColor": ["blue"],
    "foliageColor": ["dark-green"],
    "fallColor": [],
    "bloomSeason": ["spring"],
    "form": "prostrate, trailing",
    "pollinators": ["bees"],
    "wildlifeValue": [],
    "resistances": ["deer", "rabbit", "drought"],
    "commonSizes": [],
    "designUses": ["groundcover", "container", "slope-stabilization", "border"],
    "notes": "Cascading habit; excellent for walls and slopes. A low-growing rosemary that drapes beautifully over edges."
  },
  {
    "commonName": "Salem Rosemary",
    "scientificName": "Salvia rosmarinus",
    "genus": "Salvia",
    "species": "rosmarinus",
    "cultivar": "Salem",
    "plantType": "shrub",
    "category": "edible",
    "tags": ["herb", "fragrant", "drought-tolerant", "evergreen", "cold-hardy"],
    "matureHeightMin": 2,
    "matureHeightMax": 4,
    "matureSpreadMin": 2,
    "matureSpreadMax": 4,
    "growthRate": "moderate",
    "sunExposure": ["full-sun"],
    "waterNeeds": "low",
    "soilType": ["well-drained", "sand", "loam"],
    "evergreenOrDecid": "evergreen",
    "flowerColor": ["blue"],
    "foliageColor": ["dark-green"],
    "fallColor": [],
    "bloomSeason": ["spring"],
    "form": "upright, rounded",
    "pollinators": ["bees"],
    "wildlifeValue": [],
    "resistances": ["deer", "rabbit", "drought"],
    "commonSizes": [],
    "designUses": ["foundation", "border", "accent", "container"],
    "notes": "One of the most cold-hardy rosemary selections. A reliable, upright rosemary for culinary and ornamental use."
  },
  {
    "commonName": "Tuscan Blue Rosemary",
    "scientificName": "Salvia rosmarinus",
    "genus": "Salvia",
    "species": "rosmarinus",
    "cultivar": "Tuscan Blue",
    "plantType": "shrub",
    "category": "edible",
    "tags": ["herb", "fragrant", "drought-tolerant", "evergreen", "upright"],
    "matureHeightMin": 4,
    "matureHeightMax": 6,
    "matureSpreadMin": 3,
    "matureSpreadMax": 4,
    "growthRate": "fast",
    "sunExposure": ["full-sun"],
    "waterNeeds": "low",
    "soilType": ["well-drained", "sand", "loam"],
    "evergreenOrDecid": "evergreen",
    "flowerColor": ["blue"],
    "foliageColor": ["dark-green"],
    "fallColor": [],
    "bloomSeason": ["spring", "summer"],
    "form": "upright, columnar",
    "pollinators": ["bees"],
    "wildlifeValue": [],
    "resistances": ["deer", "rabbit", "drought"],
    "commonSizes": [],
    "designUses": ["foundation", "border", "accent", "hedge"],
    "notes": "Tall, strongly upright habit with broad leaves. A vigorous, columnar rosemary with intense flavor and bold blue flowers."
  },
  {
    "commonName": "African Blue Basil",
    "scientificName": "Ocimum kilimandscharicum x basilicum",
    "genus": "Ocimum",
    "species": "kilimandscharicum x basilicum",
    "cultivar": "African Blue",
    "plantType": "annual",
    "category": "edible",
    "tags": ["herb", "pollinator", "sterile-hybrid", "long-blooming"],
    "matureHeightMin": 2,
    "matureHeightMax": 4,
    "matureSpreadMin": 2,
    "matureSpreadMax": 3,
    "growthRate": "fast",
    "sunExposure": ["full-sun"],
    "waterNeeds": "moderate",
    "soilType": ["loam", "well-drained"],
    "evergreenOrDecid": "deciduous",
    "flowerColor": ["purple", "blue"],
    "foliageColor": ["green", "purple"],
    "fallColor": [],
    "bloomSeason": ["summer", "fall"],
    "form": "upright, bushy",
    "pollinators": ["bees", "butterflies"],
    "wildlifeValue": [],
    "resistances": [],
    "commonSizes": [],
    "designUses": ["border", "container", "mass-planting"],
    "notes": "Sterile hybrid; blooms continuously without going to seed. A top pollinator plant with ornamental purple-veined foliage."
  },
  {
    "commonName": "Prospera Basil",
    "scientificName": "Ocimum basilicum",
    "genus": "Ocimum",
    "species": "basilicum",
    "cultivar": "Prospera",
    "plantType": "annual",
    "category": "edible",
    "tags": ["herb", "downy-mildew-resistant", "culinary"],
    "matureHeightMin": 1.5,
    "matureHeightMax": 2,
    "matureSpreadMin": 1,
    "matureSpreadMax": 1.5,
    "growthRate": "fast",
    "sunExposure": ["full-sun"],
    "waterNeeds": "moderate",
    "soilType": ["loam", "well-drained"],
    "evergreenOrDecid": "deciduous",
    "flowerColor": ["white"],
    "foliageColor": ["green"],
    "fallColor": [],
    "bloomSeason": ["summer"],
    "form": "upright, bushy",
    "pollinators": ["bees"],
    "wildlifeValue": [],
    "resistances": ["downy-mildew"],
    "commonSizes": [],
    "designUses": ["container", "border"],
    "notes": "Downy mildew resistant sweet basil. A breakthrough culinary basil that stays healthy when others succumb to disease."
  },
  {
    "commonName": "Curled Parsley",
    "scientificName": "Petroselinum crispum",
    "genus": "Petroselinum",
    "species": "crispum",
    "variety": "crispum",
    "cultivar": null,
    "plantType": "annual",
    "category": "edible",
    "tags": ["herb", "culinary", "biennial"],
    "matureHeightMin": 0.75,
    "matureHeightMax": 1,
    "matureSpreadMin": 0.75,
    "matureSpreadMax": 1,
    "growthRate": "moderate",
    "sunExposure": ["full-sun", "part-shade"],
    "waterNeeds": "moderate",
    "soilType": ["loam", "well-drained"],
    "evergreenOrDecid": "deciduous",
    "flowerColor": ["yellow-green"],
    "foliageColor": ["green"],
    "fallColor": [],
    "bloomSeason": ["summer"],
    "form": "compact, mounding",
    "pollinators": ["butterflies"],
    "wildlifeValue": ["butterflies"],
    "resistances": [],
    "commonSizes": [],
    "designUses": ["container", "border"],
    "notes": "Tightly curled leaves; biennial grown as annual. Host plant for swallowtail butterflies."
  },
  {
    "commonName": "Italian Parsley",
    "scientificName": "Petroselinum crispum",
    "genus": "Petroselinum",
    "species": "crispum",
    "variety": "neapolitanum",
    "cultivar": null,
    "plantType": "annual",
    "category": "edible",
    "tags": ["herb", "culinary", "biennial", "flat-leaf"],
    "matureHeightMin": 1,
    "matureHeightMax": 1.5,
    "matureSpreadMin": 0.75,
    "matureSpreadMax": 1,
    "growthRate": "moderate",
    "sunExposure": ["full-sun", "part-shade"],
    "waterNeeds": "moderate",
    "soilType": ["loam", "well-drained"],
    "evergreenOrDecid": "deciduous",
    "flowerColor": ["yellow-green"],
    "foliageColor": ["green"],
    "fallColor": [],
    "bloomSeason": ["summer"],
    "form": "upright, mounding",
    "pollinators": ["butterflies"],
    "wildlifeValue": ["butterflies"],
    "resistances": [],
    "commonSizes": [],
    "designUses": ["container", "border"],
    "notes": "Flat-leaf variety; stronger flavor than curled. Preferred culinary parsley; host plant for swallowtails."
  },
  {
    "commonName": "Tricolor Sage",
    "scientificName": "Salvia officinalis",
    "genus": "Salvia",
    "species": "officinalis",
    "cultivar": "Tricolor",
    "plantType": "perennial",
    "category": "edible",
    "tags": ["herb", "fragrant", "ornamental", "variegated"],
    "matureHeightMin": 1,
    "matureHeightMax": 1.5,
    "matureSpreadMin": 1.5,
    "matureSpreadMax": 2,
    "growthRate": "moderate",
    "sunExposure": ["full-sun"],
    "waterNeeds": "low",
    "soilType": ["well-drained", "sand", "loam"],
    "evergreenOrDecid": "evergreen",
    "flowerColor": ["blue-purple"],
    "foliageColor": ["green", "white", "pink"],
    "fallColor": [],
    "bloomSeason": ["summer"],
    "form": "compact, mounding",
    "pollinators": ["bees"],
    "wildlifeValue": [],
    "resistances": ["deer", "rabbit", "drought"],
    "commonSizes": [],
    "designUses": ["border", "container", "accent"],
    "notes": "Variegated foliage in green, white, and pink. An ornamental culinary sage with striking tricolor leaves."
  },
  {
    "commonName": "Purple Sage",
    "scientificName": "Salvia officinalis",
    "genus": "Salvia",
    "species": "officinalis",
    "cultivar": "Purpurascens",
    "plantType": "perennial",
    "category": "edible",
    "tags": ["herb", "fragrant", "ornamental", "purple-foliage"],
    "matureHeightMin": 1,
    "matureHeightMax": 2,
    "matureSpreadMin": 1.5,
    "matureSpreadMax": 2.5,
    "growthRate": "moderate",
    "sunExposure": ["full-sun"],
    "waterNeeds": "low",
    "soilType": ["well-drained", "sand", "loam"],
    "evergreenOrDecid": "evergreen",
    "flowerColor": ["blue-purple"],
    "foliageColor": ["purple", "grey-green"],
    "fallColor": [],
    "bloomSeason": ["summer"],
    "form": "compact, mounding",
    "pollinators": ["bees"],
    "wildlifeValue": [],
    "resistances": ["deer", "rabbit", "drought"],
    "commonSizes": [],
    "designUses": ["border", "container", "accent"],
    "notes": "Purple-tinted foliage; culinary and ornamental. A beautiful dual-purpose sage with smoky purple leaves."
  },
  {
    "commonName": "Berggarten Sage",
    "scientificName": "Salvia officinalis",
    "genus": "Salvia",
    "species": "officinalis",
    "cultivar": "Berggarten",
    "plantType": "perennial",
    "category": "edible",
    "tags": ["herb", "fragrant", "ornamental", "broad-leaf", "non-flowering"],
    "matureHeightMin": 1,
    "matureHeightMax": 2,
    "matureSpreadMin": 2,
    "matureSpreadMax": 3,
    "growthRate": "moderate",
    "sunExposure": ["full-sun"],
    "waterNeeds": "low",
    "soilType": ["well-drained", "sand", "loam"],
    "evergreenOrDecid": "evergreen",
    "flowerColor": [],
    "foliageColor": ["silver-green"],
    "fallColor": [],
    "bloomSeason": [],
    "form": "compact, mounding",
    "pollinators": [],
    "wildlifeValue": [],
    "resistances": ["deer", "rabbit", "drought"],
    "commonSizes": [],
    "designUses": ["border", "container", "accent", "mass-planting"],
    "notes": "Extra-large rounded leaves; rarely flowers. A top culinary sage with broad, silvery-green foliage and excellent texture."
  },
  {
    "commonName": "Silver Edge Thyme",
    "scientificName": "Thymus vulgaris",
    "genus": "Thymus",
    "species": "vulgaris",
    "cultivar": "Silver Edge",
    "plantType": "perennial",
    "category": "edible",
    "tags": ["herb", "fragrant", "variegated", "groundcover", "drought-tolerant"],
    "matureHeightMin": 0.5,
    "matureHeightMax": 0.75,
    "matureSpreadMin": 0.75,
    "matureSpreadMax": 1,
    "growthRate": "slow",
    "sunExposure": ["full-sun"],
    "waterNeeds": "low",
    "soilType": ["well-drained", "sand", "loam"],
    "evergreenOrDecid": "evergreen",
    "flowerColor": ["pink"],
    "foliageColor": ["green", "white"],
    "fallColor": [],
    "bloomSeason": ["summer"],
    "form": "compact, mounding",
    "pollinators": ["bees"],
    "wildlifeValue": [],
    "resistances": ["deer", "rabbit", "drought"],
    "commonSizes": [],
    "designUses": ["border", "container", "groundcover"],
    "notes": "White-edged variegated foliage. An ornamental thyme with silver-white leaf margins and culinary use."
  },
  {
    "commonName": "Golden Lemon Thyme",
    "scientificName": "Thymus citriodorus",
    "genus": "Thymus",
    "species": "citriodorus",
    "cultivar": "Aureus",
    "plantType": "perennial",
    "category": "edible",
    "tags": ["herb", "fragrant", "lemon-scented", "groundcover", "drought-tolerant", "golden-foliage"],
    "matureHeightMin": 0.5,
    "matureHeightMax": 0.75,
    "matureSpreadMin": 0.75,
    "matureSpreadMax": 1,
    "growthRate": "slow",
    "sunExposure": ["full-sun"],
    "waterNeeds": "low",
    "soilType": ["well-drained", "sand", "loam"],
    "evergreenOrDecid": "evergreen",
    "flowerColor": ["pink"],
    "foliageColor": ["golden", "green"],
    "fallColor": [],
    "bloomSeason": ["summer"],
    "form": "compact, mounding",
    "pollinators": ["bees"],
    "wildlifeValue": [],
    "resistances": ["deer", "rabbit", "drought"],
    "commonSizes": [],
    "designUses": ["border", "container", "groundcover"],
    "notes": "Lemon-scented golden foliage. A bright, citrusy thyme with ornamental and culinary value."
  },
  {
    "commonName": "Peppermint",
    "scientificName": "Mentha x piperita",
    "genus": "Mentha",
    "species": "x piperita",
    "cultivar": null,
    "plantType": "perennial",
    "category": "edible",
    "tags": ["herb", "fragrant", "spreading", "culinary", "vigorous"],
    "matureHeightMin": 1,
    "matureHeightMax": 2,
    "matureSpreadMin": 2,
    "matureSpreadMax": 4,
    "growthRate": "fast",
    "sunExposure": ["full-sun", "part-shade"],
    "waterNeeds": "moderate",
    "soilType": ["loam", "moist"],
    "evergreenOrDecid": "deciduous",
    "flowerColor": ["purple"],
    "foliageColor": ["dark-green"],
    "fallColor": [],
    "bloomSeason": ["summer"],
    "form": "spreading",
    "pollinators": ["bees", "butterflies"],
    "wildlifeValue": [],
    "resistances": ["deer", "rabbit"],
    "commonSizes": [],
    "designUses": ["container", "border"],
    "notes": "Aggressive spreader  best in containers. A vigorous mint with strong peppermint flavor and aroma."
  },
  {
    "commonName": "Red Veined Dock",
    "scientificName": "Rumex sanguineus",
    "genus": "Rumex",
    "species": "sanguineus",
    "cultivar": null,
    "plantType": "perennial",
    "category": "edible",
    "tags": ["herb", "ornamental", "edible-green", "red-veined"],
    "matureHeightMin": 1,
    "matureHeightMax": 1.5,
    "matureSpreadMin": 0.75,
    "matureSpreadMax": 1,
    "growthRate": "moderate",
    "sunExposure": ["full-sun", "part-shade"],
    "waterNeeds": "moderate",
    "soilType": ["loam", "moist", "well-drained"],
    "evergreenOrDecid": "deciduous",
    "flowerColor": ["green"],
    "foliageColor": ["green", "red"],
    "fallColor": [],
    "bloomSeason": ["summer"],
    "form": "upright, clumping",
    "pollinators": [],
    "wildlifeValue": [],
    "resistances": ["deer"],
    "commonSizes": [],
    "designUses": ["border", "accent", "container"],
    "notes": "Striking red-veined foliage; edible leaves with lemony flavor. An ornamental herb that doubles as an eye-catching garden accent."
  },
  {
    "commonName": "Mountain Mint",
    "scientificName": "Pycnanthemum muticum",
    "genus": "Pycnanthemum",
    "species": "muticum",
    "cultivar": null,
    "plantType": "perennial",
    "category": "native",
    "tags": ["herb", "native", "pollinator", "fragrant", "low-maintenance"],
    "matureHeightMin": 2,
    "matureHeightMax": 3,
    "matureSpreadMin": 2,
    "matureSpreadMax": 3,
    "growthRate": "moderate",
    "sunExposure": ["full-sun", "part-shade"],
    "waterNeeds": "low",
    "soilType": ["loam", "clay", "well-drained"],
    "evergreenOrDecid": "deciduous",
    "flowerColor": ["white"],
    "foliageColor": ["silver-green"],
    "fallColor": [],
    "bloomSeason": ["summer"],
    "form": "upright, clumping",
    "pollinators": ["bees", "butterflies", "hummingbirds"],
    "wildlifeValue": ["birds"],
    "resistances": ["deer", "rabbit", "drought"],
    "commonSizes": [],
    "designUses": ["border", "mass-planting", "accent"],
    "notes": "One of the top native pollinator plants. A tough native herb with silvery bracts and intense minty fragrance that bees love."
  }
]
